{"learner":{"attributes":{"niter":"109"},"feature_names":[],"feature_types":[],"gradient_booster":{"model":{"gbtree_model_param":{"num_parallel_tree":"1","num_trees":"110","size_leaf_vector":"0"},"tree_info":[0,0,0,0,0,0,0,0,0,0,0,0,0,0,0,0,0,0,0,0,0,0,0,0,0,0,0,0,0,0,0,0,0,0,0,0,0,0,0,0,0,0,0,0,0,0,0,0,0,0,0,0,0,0,0,0,0,0,0,0,0,0,0,0,0,0,0,0,0,0,0,0,0,0,0,0,0,0,0,0,0,0,0,0,0,0,0,0,0,0,0,0,0,0,0,0,0,0,0,0,0,0,0,0,0,0,0,0,0,0],"trees":[{"base_weights":[3.448276E-1,9.0909094E-1,-9.0909094E-1,1.5E0,-4E-1],"categories":[],"categories_nodes":[],"categories_segments":[],"categories_sizes":[],"default_left":[1,1,0,0,0],"id":0,"left_children":[1,3,-1,-1,-1],"loss_changes":[5.956113E0,4.854545E0,0E0,0E0,0E0],"parents":[2147483647,0,0,1,1],"right_children":[2,4,-1,-1,-1],"split_conditions":[2.0626429E-1,8.363527E-2,-9.090909E-3,1.5E-2,-4E-3],"split_indices":[2,3,0,0,0],"split_type":[0,0,0,0,0],"sum_hessian":[6.25E0,4.5E0,1.75E0,3E0,1.5E0],"tree_param":{"num_deleted":"0","num_feature":"53","num_nodes":"5","size_leaf_vector":"0"}},{"base_weights":[3.7297663E-1,-3.6174253E-1,1.4209834E0,6.631356E-1,-8.192039E-1,-1.3285582E0,2.240334E-1],"categories":[],"categories_nodes":[],"categories_segments":[],"categories_sizes":[],"default_left":[1,1,0,0,1,0,0],"id":1,"left_children":[1,3,-1,-1,5,-1,-1],"loss_changes":[6.6737823E0,3.1218245E0,0E0,0E0,2.5559638E0,0E0,0E0],"parents":[2147483647,0,0,1,1,4,4],"right_children":[2,4,-1,-1,6,-1,-1],"split_conditions":[1.1831716E-1,-4.4904433E-2,1.4209834E-2,6.6313557E-3,2.7518627E-1,-1.3285582E-2,2.240334E-3],"split_indices":[26,42,0,0,42,0,0],"split_type":[0,0,0,0,0,0,0],"sum_hessian":[6.9997735E0,4.499892E0,2.4998813E0,1.2499516E0,3.2499406E0,1.9999712E0,1.2499695E0],"tree_param":{"num_deleted":"0","num_feature":"53","num_nodes":"7","size_leaf_vector":"0"}},{"base_weights":[3.171398E-1,8.9884895E-1,-7.648286E-1,1.4777488E-1,1.3733385E0],"categories":[],"categories_nodes":[],"categories_segments":[],"categories_sizes":[],"default_left":[1,1,0,0,0],"id":2,"left_children":[1,3,-1,-1,-1],"loss_changes":[5.564873E0,1.7569599E0,0E0,0E0,0E0],"parents":[2147483647,0,0,1,1],"right_children":[2,4,-1,-1,-1],"split_conditions":[1.606937E-1,-3.3690345E-1,-7.648286E-3,1.4777487E-3,1.3733384E-2],"split_indices":[49,49,0,0,0],"split_type":[0,0,0,0,0],"sum_hessian":[6.7494097E0,4.4995303E0,2.2498794E0,2.2497766E0,2.2497537E0],"tree_param":{"num_deleted":"0","num_feature":"53","num_nodes":"5","size_leaf_vector":"0"}},{"base_weights":[4.7847545E-1,1.1175889E0,-4.4450736E-1,1.5117222E0,5.639714E-4,-1.1881908E0,3.2344127E-1],"categories":[],"categories_nodes":[],"categories_segments":[],"categories_sizes":[],"default_left":[1,1,1,0,0,0,0],"id":3,"left_children":[1,3,5,-1,-1,-1,-1],"loss_changes":[5.952526E0,2.5303106E0,2.953999E0,0E0,0E0,0E0,0E0],"parents":[2147483647,0,0,1,1,2,2],"right_children":[2,4,6,-1,-1,-1,-1],"split_conditions":[9.492395E-3,1.5060958E-1,-7.6089084E-2,1.51172215E-2,5.639714E-6,-1.18819075E-2,3.2344125E-3],"split_indices":[4,42,26,0,0,0,0],"split_type":[0,0,0,0,0,0,0],"sum_hessian":[8.248746E0,4.749288E0,3.4994583E0,3.249412E0,1.4998759E0,1.4998107E0,1.9996476E0],"tree_param":{"num_deleted":"0","num_feature":"53","num_nodes":"7","size_leaf_vector":"0"}},{"base_weights":[5.6742257E-1,1.3752173E0,-6.6078234E-1,-5.448299E-4,-1.1006325E0],"categories":[],"categories_nodes":[],"categories_segments":[],"categories_sizes":[],"default_left":[1,0,1,0,0],"id":4,"left_children":[1,-1,3,-1,-1],"loss_changes":[8.595927E0,0E0,1.0882952E0,0E0,0E0],"parents":[2147483647,0,0,2,2],"right_children":[2,-1,4,-1,-1],"split_conditions":[1.4081927E-1,1.3752173E-2,8.820863E-2,-5.4482985E-6,-1.10063255E-2],"split_indices":[31,0,3,0,0],"split_type":[0,0,0,0,0],"sum_hessian":[6.7481275E0,3.9985619E0,2.7495656E0,1.4996915E0,1.249874E0],"tree_param":{"num_deleted":"0","num_feature":"53","num_nodes":"5","size_leaf_vector":"0"}},{"base_weights":[5.596584E-1,1.0955856E0,-6.5373677E-1,1.5186185E0,-2.3717165E-1],"categories":[],"categories_nodes":[],"categories_segments":[],"categories_sizes":[],"default_left":[1,1,0,0,0],"id":5,"left_children":[1,3,-1,-1,-1],"loss_changes":[5.753984E0,3.6004806E0,0E0,0E0,0E0],"parents":[2147483647,0,0,1,1],"right_children":[2,4,-1,-1,-1],"split_conditions":[1.6788453E-1,1.0764974E-1,-6.5373676E-3,1.5186184E-2,-2.3717165E-3],"split_indices":[31,28,0,0,0],"split_type":[0,0,0,0,0],"sum_hessian":[6.7469254E0,4.747265E0,1.9996605E0,3.4976223E0,1.2496426E0],"tree_param":{"num_deleted":"0","num_feature":"53","num_nodes":"5","size_leaf_vector":"0"}},{"base_weights":[2.235974E-1,7.680645E-1,-1.0853906E0,-2.402975E-2,1.3040352E0],"categories":[],"categories_nodes":[],"categories_segments":[],"categories_sizes":[],"default_left":[1,1,0,0,0],"id":6,"left_children":[1,3,-1,-1,-1],"loss_changes":[5.285396E0,2.1527615E0,0E0,0E0,0E0],"parents":[2147483647,0,0,1,1],"right_children":[2,4,-1,-1,-1],"split_conditions":[5.252389E-1,-2.722023E-1,-1.0853905E-2,-2.402975E-4,1.3040352E-2],"split_indices":[15,40,0,0,0],"split_type":[0,0,0,0,0],"sum_hessian":[5.246304E0,3.9970067E0,1.2492973E0,1.9985614E0,1.9984453E0],"tree_param":{"num_deleted":"0","num_feature":"53","num_nodes":"5","size_leaf_vector":"0"}},{"base_weights":[1.8492985E-1,9.034898E-1,-8.4278005E-1,-2.877752E-2,1.3426497E0,-1.099718E0,-2.1101274E-1],"categories":[],"categories_nodes":[],"categories_segments":[],"categories_sizes":[],"default_left":[1,1,1,0,0,0,0],"id":7,"left_children":[1,3,5,-1,-1,-1,-1],"loss_changes":[6.1115627E0,1.9818585E0,3.3584213E-1,0E0,0E0,0E0,0E0],"parents":[2147483647,0,0,1,1,2,2],"right_children":[2,4,6,-1,-1,-1,-1],"split_conditions":[1.2622304E-1,-1.00920826E-1,2.1915138E-1,-2.8777518E-4,1.3426497E-2,-1.099718E-2,-2.1101274E-3],"split_indices":[25,37,34,0,0,0,0],"split_type":[0,0,0,0,0,0,0],"sum_hessian":[6.2448583E0,3.7463415E0,2.498517E0,1.4988948E0,2.2474465E0,1.2496054E0,1.2489116E0],"tree_param":{"num_deleted":"0","num_feature":"53","num_nodes":"7","size_leaf_vector":"0"}},{"base_weights":[3.8179904E-1,1.4497484E0,-4.2713395E-1,-9.934796E-1,5.518396E-1,-2.3933057E-1,-1.2491556E0],"categories":[],"categories_nodes":[],"categories_segments":[],"categories_sizes":[],"default_left":[1,0,1,1,0,0,0],"id":8,"left_children":[1,-1,3,5,-1,-1,-1],"loss_changes":[8.17302E0,0E0,3.7349665E0,4.7198367E-1,0E0,0E0,0E0],"parents":[2147483647,0,0,2,2,3,3],"right_children":[2,-1,4,6,-1,-1,-1],"split_conditions":[-2.9929748E-1,1.4497484E-2,3.2763854E-1,-3.167264E-2,5.518396E-3,-2.3933058E-3,-1.2491556E-2],"split_indices":[12,0,12,13,0,0,0],"split_type":[0,0,0,0,0,0,0],"sum_hessian":[7.743822E0,2.996148E0,4.747674E0,2.9983068E0,1.749367E0,1.2493271E0,1.7489797E0],"tree_param":{"num_deleted":"0","num_feature":"53","num_nodes":"7","size_leaf_vector":"0"}},{"base_weights":[3.993203E-1,1.1153668E0,-7.692882E-1,1.3790509E0,2.0923473E-1],"categories":[],"categories_nodes":[],"categories_segments":[],"categories_sizes":[],"default_left":[1,1,0,0,0],"id":9,"left_children":[1,3,-1,-1,-1],"loss_changes":[6.710202E0,8.4512377E-1,0E0,0E0,0E0],"parents":[2147483647,0,0,1,1],"right_children":[2,4,-1,-1,-1],"split_conditions":[1.24537855E-1,-2.7875203E-1,-7.692882E-3,1.3790508E-2,2.0923472E-3],"split_indices":[28,4,0,0,0],"split_type":[0,0,0,0,0],"sum_hessian":[5.993686E0,3.7447248E0,2.2489614E0,2.4963725E0,1.2483525E0],"tree_param":{"num_deleted":"0","num_feature":"53","num_nodes":"5","size_leaf_vector":"0"}},{"base_weights":[2.4202436E-1,9.893031E-1,-5.9038574E-1,1.4068542E0,-3.2434735E-2,-1.0699699E0,1.9102503E-1],"categories":[],"categories_nodes":[],"categories_segments":[],"categories_sizes":[],"default_left":[1,1,1,0,0,0,0],"id":10,"left_children":[1,3,5,-1,-1,-1,-1],"loss_changes":[6.331517E0,2.282237E0,2.0770712E0,0E0,0E0,0E0,0E0],"parents":[2147483647,0,0,1,1,2,2],"right_children":[2,4,6,-1,-1,-1,-1],"split_conditions":[-1.5738286E-1,2.5711876E-1,3.6378628E-1,1.4068541E-2,-3.2434735E-4,-1.0699699E-2,1.9102503E-3],"split_indices":[31,26,12,0,0,0,0],"split_type":[0,0,0,0,0,0,0],"sum_hessian":[8.239638E0,4.2425227E0,3.997116E0,2.7441533E0,1.4983693E0,2.2480905E0,1.7490257E0],"tree_param":{"num_deleted":"0","num_feature":"53","num_nodes":"7","size_leaf_vector":"0"}},{"base_weights":[4.333771E-1,9.0913147E-1,-8.9081895E-1,1.2093356E0,-2.2797047E-1,1.7973404E-1,1.4696978E0],"categories":[],"categories_nodes":[],"categories_segments":[],"categories_sizes":[],"default_left":[1,1,0,1,0,0,0],"id":11,"left_children":[1,3,-1,5,-1,-1,-1],"loss_changes":[6.157998E0,2.5765753E0,0E0,1.2078352E0,0E0,0E0,0E0],"parents":[2147483647,0,0,1,1,3,3],"right_children":[2,4,-1,6,-1,-1,-1],"split_conditions":[4.0232897E-1,3.016677E-1,-8.908189E-3,-5.039403E-1,-2.2797047E-3,1.7973403E-3,1.4696978E-2],"split_indices":[4,50,0,16,0,0,0],"split_type":[0,0,0,0,0,0,0],"sum_hessian":[7.489197E0,5.7402854E0,1.7489113E0,4.49108E0,1.2492055E0,1.2476352E0,3.2434444E0],"tree_param":{"num_deleted":"0","num_feature":"53","num_nodes":"7","size_leaf_vector":"0"}},{"base_weights":[3.2127947E-1,7.1081746E-1,-1.0757539E0,-3.8637113E-2,1.2490523E0,8.550608E-1,-1.1123447E0],"categories":[],"categories_nodes":[],"categories_segments":[],"categories_sizes":[],"default_left":[1,1,0,1,0,0,0],"id":12,"left_children":[1,3,-1,5,-1,-1,-1],"loss_changes":[5.383815E0,2.9685237E0,0E0,4.7855396E0,0E0,0E0,0E0],"parents":[2147483647,0,0,1,1,3,3],"right_children":[2,4,-1,6,-1,-1,-1],"split_conditions":[6.443937E-1,-9.84679E-2,-1.0757539E-2,-3.6360174E-1,1.2490523E-2,8.550608E-3,-1.1123447E-2],"split_indices":[14,14,0,6,0,0,0],"split_type":[0,0,0,0,0,0,0],"sum_hessian":[7.4880023E0,6.2394404E0,1.2485621E0,2.9959726E0,3.2434678E0,1.7461807E0,1.2497919E0],"tree_param":{"num_deleted":"0","num_feature":"53","num_nodes":"7","size_leaf_vector":"0"}},{"base_weights":[4.9178088E-1,1.3497366E0,-1.0430719E0],"categories":[],"categories_nodes":[],"categories_segments":[],"categories_sizes":[],"default_left":[1,0,0],"id":13,"left_children":[1,-1,-1],"loss_changes":[1.1265286E1,0E0,0E0],"parents":[2147483647,0,0],"right_children":[2,-1,-1],"split_conditions":[2.287718E-1,1.3497366E-2,-1.0430719E-2],"split_indices":[31,0,0],"split_type":[0,0,0],"sum_hessian":[6.4856834E0,4.2375665E0,2.2481167E0],"tree_param":{"num_deleted":"0","num_feature":"53","num_nodes":"3","size_leaf_vector":"0"}},{"base_weights":[4.1950068E-1,1.1879141E0,-5.775288E-1,1.8670116E-1,-1.0845215E0],"categories":[],"categories_nodes":[],"categories_segments":[],"categories_sizes":[],"default_left":[1,0,1,0,0],"id":14,"left_children":[1,-1,3,-1,-1],"loss_changes":[5.656375E0,0E0,1.5572696E0,0E0,0E0],"parents":[2147483647,0,0,2,2],"right_children":[2,-1,4,-1,-1],"split_conditions":[8.427672E-3,1.1879141E-2,-1.5751608E-1,1.8670115E-3,-1.0845215E-2],"split_indices":[4,0,31,0,0],"split_type":[0,0,0,0,0],"sum_hessian":[5.48756E0,2.9909627E0,2.4965973E0,1.2476557E0,1.2489414E0],"tree_param":{"num_deleted":"0","num_feature":"53","num_nodes":"5","size_leaf_vector":"0"}},{"base_weights":[2.3085022E-1,1.3509264E0,-5.9837925E-1,1.2328727E-1,-1.2327727E0],"categories":[],"categories_nodes":[],"categories_segments":[],"categories_sizes":[],"default_left":[1,0,1,0,0],"id":15,"left_children":[1,-1,3,-1,-1],"loss_changes":[7.75815E0,0E0,2.4376612E0,0E0,0E0],"parents":[2147483647,0,0,2,2],"right_children":[2,-1,4,-1,-1],"split_conditions":[-1.6748837E-1,1.3509263E-2,8.820863E-2,1.2328726E-3,-1.2327727E-2],"split_indices":[48,0,3,0,0],"split_type":[0,0,0,0,0],"sum_hessian":[6.4825387E0,2.4900227E0,3.9925163E0,2.2446887E0,1.7478274E0],"tree_param":{"num_deleted":"0","num_feature":"53","num_nodes":"5","size_leaf_vector":"0"}},{"base_weights":[1.05980515E-1,1.0535517E0,-6.5337586E-1,1.9956441E-1,-1.0424322E0],"categories":[],"categories_nodes":[],"categories_segments":[],"categories_sizes":[],"default_left":[1,0,1,0,0],"id":16,"left_children":[1,-1,3,-1,-1],"loss_changes":[5.712035E0,0E0,1.6990013E0,0E0,0E0],"parents":[2147483647,0,0,2,2],"right_children":[2,-1,4,-1,-1],"split_conditions":[-4.8187755E-2,1.0535517E-2,-3.368102E-1,1.995644E-3,-1.04243215E-2],"split_indices":[30,0,10,0,0],"split_type":[0,0,0,0,0],"sum_hessian":[5.981738E0,2.4887264E0,3.4930117E0,1.2467588E0,2.246253E0],"tree_param":{"num_deleted":"0","num_feature":"53","num_nodes":"5","size_leaf_vector":"0"}},{"base_weights":[3.360931E-1,1.3313348E0,-5.602674E-1,-1.2332021E0,4.0444434E-1],"categories":[],"categories_nodes":[],"categories_segments":[],"categories_sizes":[],"default_left":[1,0,1,0,0],"id":17,"left_children":[1,-1,3,-1,-1],"loss_changes":[6.749675E0,0E0,3.2543678E0,0E0,0E0],"parents":[2147483647,0,0,2,2],"right_children":[2,-1,4,-1,-1],"split_conditions":[-1.3484615E-1,1.3313348E-2,3.6378628E-1,-1.233202E-2,4.0444434E-3],"split_indices":[31,0,12,0,0],"split_type":[0,0,0,0,0],"sum_hessian":[5.7299657E0,2.485269E0,3.2446966E0,1.7474506E0,1.4972459E0],"tree_param":{"num_deleted":"0","num_feature":"53","num_nodes":"5","size_leaf_vector":"0"}},{"base_weights":[2.8343996E-1,1.2285565E0,-3.093387E-1,-7.755534E-1,6.554181E-1,1.5064746E-1,-1.2491338E0],"categories":[],"categories_nodes":[],"categories_segments":[],"categories_sizes":[],"default_left":[1,0,1,1,0,0,0],"id":18,"left_children":[1,-1,3,5,-1,-1,-1],"loss_changes":[4.425914E0,0E0,2.8637915E0,1.9377604E0,0E0,0E0,0E0],"parents":[2147483647,0,0,2,2,3,3],"right_children":[2,-1,4,6,-1,-1,-1],"split_conditions":[-4.1297102E-1,1.2285565E-2,3.6378628E-1,4.0475547E-2,6.5541808E-3,1.5064746E-3,-1.2491338E-2],"split_indices":[31,0,12,28,0,0,0],"split_type":[0,0,0,0,0,0,0],"sum_hessian":[6.2216167E0,1.984702E0,4.2369146E0,2.9887357E0,1.2481791E0,1.2418653E0,1.7468704E0],"tree_param":{"num_deleted":"0","num_feature":"53","num_nodes":"7","size_leaf_vector":"0"}},{"base_weights":[5.988442E-1,1.2724786E0,-4.1259417E-1,1.8217053E-1,-7.820791E-1],"categories":[],"categories_nodes":[],"categories_segments":[],"categories_sizes":[],"default_left":[1,0,1,0,0],"id":19,"left_children":[1,-1,3,-1,-1],"loss_changes":[5.6133113E0,0E0,9.644992E-1,0E0,0E0],"parents":[2147483647,0,0,2,2],"right_children":[2,-1,4,-1,-1],"split_conditions":[9.492395E-3,1.2724785E-2,-8.085814E-2,1.8217053E-3,-7.820791E-3],"split_indices":[4,0,19,0,0],"split_type":[0,0,0,0,0],"sum_hessian":[6.468073E0,3.7274456E0,2.7406273E0,1.2444235E0,1.4962039E0],"tree_param":{"num_deleted":"0","num_feature":"53","num_nodes":"5","size_leaf_vector":"0"}},{"base_weights":[2.8954184E-1,8.6021584E-1,-1.1354896E0,-4.96917E-2,1.3591969E0],"categories":[],"categories_nodes":[],"categories_segments":[],"categories_sizes":[],"default_left":[1,1,0,0,0],"id":20,"left_children":[1,3,-1,-1,-1],"loss_changes":[6.8446813E0,2.6651387E0,0E0,0E0,0E0],"parents":[2147483647,0,0,1,1],"right_children":[2,4,-1,-1,-1],"split_conditions":[2.4496028E-1,-2.4213642E-1,-1.1354895E-2,-4.96917E-4,1.3591968E-2],"split_indices":[34,10,0,0,0],"split_type":[0,0,0,0,0],"sum_hessian":[6.2155805E0,4.7212443E0,1.494336E0,1.9910026E0,2.7302418E0],"tree_param":{"num_deleted":"0","num_feature":"53","num_nodes":"5","size_leaf_vector":"0"}},{"base_weights":[3.5047242E-1,9.8494625E-1,-1.1799039E0,1.3701648E0,-2.262805E-2],"categories":[],"categories_nodes":[],"categories_segments":[],"categories_sizes":[],"default_left":[1,1,0,0,0],"id":21,"left_children":[1,3,-1,-1,-1],"loss_changes":[7.924819E0,2.153552E0,0E0,0E0,0E0],"parents":[2147483647,0,0,1,1],"right_children":[2,4,-1,-1,-1],"split_conditions":[4.1537783E-1,1.3467827E-1,-1.1799038E-2,1.37016475E-2,-2.2628049E-4],"split_indices":[11,28,0,0,0],"split_type":[0,0,0,0,0],"sum_hessian":[5.9647684E0,4.4685636E0,1.496205E0,2.9723153E0,1.4962484E0],"tree_param":{"num_deleted":"0","num_feature":"53","num_nodes":"5","size_leaf_vector":"0"}},{"base_weights":[5.1166713E-1,1.0326012E0,-6.557776E-1,1.4827089E-1,1.2445272E0],"categories":[],"categories_nodes":[],"categories_segments":[],"categories_sizes":[],"default_left":[1,1,0,0,0],"id":22,"left_children":[1,3,-1,-1,-1],"loss_changes":[5.36516E0,8.871918E-1,0E0,0E0,0E0],"parents":[2147483647,0,0,1,1],"right_children":[2,4,-1,-1,-1],"split_conditions":[8.820863E-2,-2.1417314E-1,-6.5577757E-3,1.4827088E-3,1.2445272E-2],"split_indices":[3,34,0,0,0],"split_type":[0,0,0,0,0],"sum_hessian":[6.70848E0,4.718504E0,1.9899757E0,1.240741E0,3.477763E0],"tree_param":{"num_deleted":"0","num_feature":"53","num_nodes":"5","size_leaf_vector":"0"}},{"base_weights":[2.7029496E-2,4.7707132E-1,-8.811475E-1,-5.826608E-1,1.1277858E0],"categories":[],"categories_nodes":[],"categories_segments":[],"categories_sizes":[],"default_left":[1,1,0,0,0],"id":23,"left_children":[1,3,-1,-1,-1],"loss_changes":[3.3735216E0,4.4360604E0,0E0,0E0,0E0],"parents":[2147483647,0,0,1,1],"right_children":[2,4,-1,-1,-1],"split_conditions":[3.6890033E-1,-1.3591293E-1,-8.811475E-3,-5.826608E-3,1.1277858E-2],"split_indices":[0,0,0,0,0],"split_type":[0,0,0,0,0],"sum_hessian":[6.225407E0,4.480042E0,1.7453653E0,1.7441539E0,2.7358882E0],"tree_param":{"num_deleted":"0","num_feature":"53","num_nodes":"5","size_leaf_vector":"0"}},{"base_weights":[3.487967E-1,9.952252E-1,-8.0851996E-1,1.4054522E-1,1.2010039E0,-2.0560093E-1,-1.0515277E0],"categories":[],"categories_nodes":[],"categories_segments":[],"categories_sizes":[],"default_left":[1,1,1,0,0,0,0],"id":24,"left_children":[1,3,5,-1,-1,-1,-1],"loss_changes":[6.938293E0,8.352194E-1,2.9514122E-1,0E0,0E0,0E0,0E0],"parents":[2147483647,0,0,1,1,2,2],"right_children":[2,4,6,-1,-1,-1,-1],"split_conditions":[1.1458213E-1,-2.6787102E-1,-2.7708006E-1,1.4054521E-3,1.2010039E-2,-2.0560094E-3,-1.0515277E-2],"split_indices":[31,50,10,0,0,0,0],"split_type":[0,0,0,0,0,0,0],"sum_hessian":[7.1987023E0,4.708686E0,2.4900165E0,1.2402852E0,3.4684005E0,1.2456186E0,1.2443979E0],"tree_param":{"num_deleted":"0","num_feature":"53","num_nodes":"7","size_leaf_vector":"0"}},{"base_weights":[3.5097274E-1,7.844678E-1,-6.684639E-1,-2.6054952E-1,1.0990474E0,1.3349817E0,2.1999903E-1],"categories":[],"categories_nodes":[],"categories_segments":[],"categories_sizes":[],"default_left":[1,1,0,0,1,0,0],"id":25,"left_children":[1,3,-1,-1,5,-1,-1],"loss_changes":[4.1492844E0,2.3295996E0,0E0,0E0,7.368436E-1,0E0,0E0],"parents":[2147483647,0,0,1,1,4,4],"right_children":[2,4,-1,-1,6,-1,-1],"split_conditions":[2.1789552E-1,-4.2792946E-1,-6.6846386E-3,-2.605495E-3,1.4662296E-1,1.3349816E-2,2.1999902E-3],"split_indices":[2,10,0,0,35,0,0],"split_type":[0,0,0,0,0,0,0],"sum_hessian":[7.2025924E0,5.2153554E0,1.9872371E0,1.2464535E0,3.9689019E0,2.720153E0,1.2487487E0],"tree_param":{"num_deleted":"0","num_feature":"53","num_nodes":"7","size_leaf_vector":"0"}},{"base_weights":[4.0230268E-1,9.470029E-1,-6.437901E-1,1.2823675E0,-2.533392E-1,-1.0737025E0,2.0581738E-3],"categories":[],"categories_nodes":[],"categories_segments":[],"categories_sizes":[],"default_left":[1,1,1,0,0,0,0],"id":26,"left_children":[1,3,5,-1,-1,-1,-1],"loss_changes":[5.8460937E0,2.9204702E0,1.0411981E0,0E0,0E0,0E0,0E0],"parents":[2147483647,0,0,1,1,2,2],"right_children":[2,4,6,-1,-1,-1,-1],"split_conditions":[1.606937E-1,8.363527E-2,1.8435729E-1,1.2823675E-2,-2.533392E-3,-1.0737024E-2,2.0581738E-5],"split_indices":[49,3,51,0,0,0,0],"split_type":[0,0,0,0,0,0,0],"sum_hessian":[8.189818E0,5.4478493E0,2.7419696E0,4.2047467E0,1.2431026E0,1.2484584E0,1.4935112E0],"tree_param":{"num_deleted":"0","num_feature":"53","num_nodes":"7","size_leaf_vector":"0"}},{"base_weights":[8.1083804E-2,8.5984546E-1,-6.250662E-1,1.2204283E-1,1.1493068E0,-1.2140808E0,1.9146848E-1],"categories":[],"categories_nodes":[],"categories_segments":[],"categories_sizes":[],"default_left":[1,1,1,0,0,0,0],"id":27,"left_children":[1,3,5,-1,-1,-1,-1],"loss_changes":[4.6387315E0,7.070677E-1,2.392097E0,0E0,0E0,0E0,0E0],"parents":[2147483647,0,0,1,1,2,2],"right_children":[2,4,6,-1,-1,-1,-1],"split_conditions":[8.751687E-2,-2.6957265E-1,3.2763854E-1,1.2204283E-3,1.1493067E-2,-1.2140808E-2,1.9146848E-3],"split_indices":[31,7,12,0,0,0,0],"split_type":[0,0,0,0,0,0,0],"sum_hessian":[6.4579067E0,2.967554E0,3.4903526E0,1.2367771E0,1.730777E0,1.7448325E0,1.7455201E0],"tree_param":{"num_deleted":"0","num_feature":"53","num_nodes":"7","size_leaf_vector":"0"}},{"base_weights":[2.819528E-1,1.0313038E0,-8.097533E-1,1.4271182E-1,1.3065937E0,-1.0835062E0,-1.7496552E-1],"categories":[],"categories_nodes":[],"categories_segments":[],"categories_sizes":[],"default_left":[1,1,1,0,0,0,0],"id":28,"left_children":[1,3,5,-1,-1,-1,-1],"loss_changes":[6.730051E0,9.6637535E-1,4.1744375E-1,0E0,0E0,0E0,0E0],"parents":[2147483647,0,0,1,1,2,2],"right_children":[2,4,6,-1,-1,-1,-1],"split_conditions":[-1.6397399E-1,-4.500686E-1,3.1754386E-1,1.4271182E-3,1.3065936E-2,-1.0835062E-2,-1.7496551E-3],"split_indices":[48,16,6,0,0,0,0],"split_type":[0,0,0,0,0,0,0],"sum_hessian":[6.205915E0,3.712779E0,2.4931362E0,1.2373184E0,2.4754605E0,1.2480385E0,1.2450975E0],"tree_param":{"num_deleted":"0","num_feature":"53","num_nodes":"7","size_leaf_vector":"0"}},{"base_weights":[1.2616706E-1,9.304871E-1,-6.5828663E-1,1.3033241E-1,1.2182566E0,1.3504127E-1,-1.2108934E0],"categories":[],"categories_nodes":[],"categories_segments":[],"categories_sizes":[],"default_left":[1,1,1,0,0,0,0],"id":29,"left_children":[1,3,5,-1,-1,-1,-1],"loss_changes":[5.4688973E0,8.1169033E-1,2.1285236E0,0E0,0E0,0E0,0E0],"parents":[2147483647,0,0,1,1,2,2],"right_children":[2,4,6,-1,-1,-1,-1],"split_conditions":[1.237395E-1,-1.653185E-1,8.363527E-2,1.3033241E-3,1.2182565E-2,1.3504126E-3,-1.2108934E-2],"split_indices":[42,3,3,0,0,0,0],"split_type":[0,0,0,0,0,0,0],"sum_hessian":[6.6968946E0,3.214662E0,3.4822326E0,1.2346299E0,1.9800322E0,1.7399588E0,1.7422739E0],"tree_param":{"num_deleted":"0","num_feature":"53","num_nodes":"7","size_leaf_vector":"0"}},{"base_weights":[4.7449565E-1,9.848633E-1,-5.2811027E-1,1.384065E-1,1.2663049E0],"categories":[],"categories_nodes":[],"categories_segments":[],"categories_sizes":[],"default_left":[1,1,0,0,0],"id":30,"left_children":[1,3,-1,-1,-1],"loss_changes":[3.698265E0,8.8840103E-1,0E0,0E0,0E0],"parents":[2147483647,0,0,1,1],"right_children":[2,4,-1,-1,-1],"split_conditions":[1.6380052E-1,-3.5777777E-1,-5.2811024E-3,1.384065E-3,1.2663048E-2],"split_indices":[42,7,0,0,0],"split_type":[0,0,0,0,0],"sum_hessian":[5.210989E0,3.464906E0,1.7460831E0,1.2368282E0,2.2280777E0],"tree_param":{"num_deleted":"0","num_feature":"53","num_nodes":"5","size_leaf_vector":"0"}},{"base_weights":[5.27109E-1,1.0457458E0,-4.2722148E-1,1.2860872E-1,1.3162713E0],"categories":[],"categories_nodes":[],"categories_segments":[],"categories_sizes":[],"default_left":[1,1,0,0,0],"id":31,"left_children":[1,3,-1,-1,-1],"loss_changes":[4.003983E0,1.0579829E0,0E0,0E0,0E0],"parents":[2147483647,0,0,1,1],"right_children":[2,4,-1,-1,-1],"split_conditions":[3.89906E-1,-3.7950635E-1,-4.2722146E-3,1.2860872E-3,1.3162713E-2],"split_indices":[31,47,0,0,0],"split_type":[0,0,0,0,0],"sum_hessian":[6.187012E0,3.946482E0,2.24053E0,1.2349956E0,2.7114863E0],"tree_param":{"num_deleted":"0","num_feature":"53","num_nodes":"5","size_leaf_vector":"0"}},{"base_weights":[3.6145344E-1,8.709665E-1,-8.757896E-1,1.2214911E0,-2.5210592E-1],"categories":[],"categories_nodes":[],"categories_segments":[],"categories_sizes":[],"default_left":[1,1,0,0,0],"id":32,"left_children":[1,3,-1,-1,-1],"loss_changes":[5.6027617E0,2.6461496E0,0E0,0E0,0E0],"parents":[2147483647,0,0,1,1],"right_children":[2,4,-1,-1,-1],"split_conditions":[4.0604192E-1,3.0327925E-1,-8.757896E-3,1.2214911E-2,-2.5210592E-3],"split_indices":[0,50,0,0,0],"split_type":[0,0,0,0,0],"sum_hessian":[6.6777344E0,4.9395885E0,1.7381454E0,3.6978204E0,1.2417682E0],"tree_param":{"num_deleted":"0","num_feature":"53","num_nodes":"5","size_leaf_vector":"0"}},{"base_weights":[3.825881E-1,8.2797617E-1,-7.893658E-1,7.5088024E-2,1.2900994E0],"categories":[],"categories_nodes":[],"categories_segments":[],"categories_sizes":[],"default_left":[1,1,0,0,0],"id":33,"left_children":[1,3,-1,-1,-1],"loss_changes":[4.404048E0,1.8844206E0,0E0,0E0,0E0],"parents":[2147483647,0,0,1,1],"right_children":[2,4,-1,-1,-1],"split_conditions":[3.9342058E-1,-2.3696402E-1,-7.893658E-3,7.508802E-4,1.2900993E-2],"split_indices":[18,18,0,0,0],"split_type":[0,0,0,0,0],"sum_hessian":[6.1851654E0,4.6945586E0,1.4906069E0,2.227696E0,2.4668627E0],"tree_param":{"num_deleted":"0","num_feature":"53","num_nodes":"5","size_leaf_vector":"0"}},{"base_weights":[3.6539307E-1,7.199156E-1,-6.1857677E-1,1.6475016E-1,1.1617619E0,9.6838015E-1,-7.056434E-1],"categories":[],"categories_nodes":[],"categories_segments":[],"categories_sizes":[],"default_left":[1,1,0,1,0,0,0],"id":34,"left_children":[1,3,-1,5,-1,-1,-1],"loss_changes":[2.6931424E0,1.0839336E0,0E0,3.110048E0,0E0,0E0,0E0],"parents":[2147483647,0,0,1,1,3,3],"right_children":[2,4,-1,6,-1,-1,-1],"split_conditions":[6.3618803E-1,-2.0179793E-2,-6.1857677E-3,-4.4176507E-1,1.1617619E-2,9.683801E-3,-7.056434E-3],"split_indices":[29,36,0,52,0,0,0],"split_type":[0,0,0,0,0,0,0],"sum_hessian":[5.4437065E0,4.1991253E0,1.2445813E0,2.4693432E0,1.7297822E0,1.2253792E0,1.2439638E0],"tree_param":{"num_deleted":"0","num_feature":"53","num_nodes":"7","size_leaf_vector":"0"}},{"base_weights":[-1.8915802E-1,9.635132E-1,-8.2396615E-1,6.25933E-2,-1.371129E0],"categories":[],"categories_nodes":[],"categories_segments":[],"categories_sizes":[],"default_left":[1,0,1,0,0],"id":35,"left_children":[1,-1,3,-1,-1],"loss_changes":[6.954326E0,0E0,2.9809155E0,0E0,0E0],"parents":[2147483647,0,0,2,2],"right_children":[2,-1,4,-1,-1],"split_conditions":[-3.6360174E-1,9.635132E-3,8.751687E-2,6.25933E-4,-1.371129E-2],"split_indices":[6,0,31,0,0],"split_type":[0,0,0,0,0],"sum_hessian":[7.4190416E0,2.4509165E0,4.968125E0,2.2340052E0,2.7341197E0],"tree_param":{"num_deleted":"0","num_feature":"53","num_nodes":"5","size_leaf_vector":"0"}},{"base_weights":[7.9231896E-2,8.1915563E-1,-1.2162862E0,1.2667446E0,-2.3518519E-1],"categories":[],"categories_nodes":[],"categories_segments":[],"categories_sizes":[],"default_left":[1,1,0,0,0],"id":36,"left_children":[1,3,-1,-1,-1],"loss_changes":[7.170907E0,2.51465E0,0E0,0E0,0E0],"parents":[2147483647,0,0,1,1],"right_children":[2,4,-1,-1,-1],"split_conditions":[1.1137165E-1,3.7303776E-2,-1.2162861E-2,1.26674455E-2,-2.351852E-3],"split_indices":[4,3,0,0,0],"split_type":[0,0,0,0,0],"sum_hessian":[5.4413505E0,3.697345E0,1.7440056E0,2.4540813E0,1.2432637E0],"tree_param":{"num_deleted":"0","num_feature":"53","num_nodes":"5","size_leaf_vector":"0"}},{"base_weights":[8.730485E-3,1.148811E0,-6.2008184E-1,5.5498314E-1,-1.155624E0],"categories":[],"categories_nodes":[],"categories_segments":[],"categories_sizes":[],"default_left":[1,0,1,0,0],"id":37,"left_children":[1,-1,3,-1,-1],"loss_changes":[5.5032153E0,0E0,3.760531E0,0E0,0E0],"parents":[2147483647,0,0,2,2],"right_children":[2,-1,4,-1,-1],"split_conditions":[-2.6124215E-1,1.148811E-2,-3.60097E-1,5.5498313E-3,-1.155624E-2],"split_indices":[19,0,4,0,0],"split_type":[0,0,0,0,0],"sum_hessian":[5.6827736E0,1.7261641E0,3.9566097E0,1.2273365E0,2.729273E0],"tree_param":{"num_deleted":"0","num_feature":"53","num_nodes":"5","size_leaf_vector":"0"}},{"base_weights":[-2.2476664E-1,5.959339E-1,-1.2362931E0,1.0982944E0,-2.7893803E-1],"categories":[],"categories_nodes":[],"categories_segments":[],"categories_sizes":[],"default_left":[1,1,0,0,0],"id":38,"left_children":[1,3,-1,-1,-1],"loss_changes":[5.6566367E0,2.0408835E0,0E0,0E0,0E0],"parents":[2147483647,0,0,1,1],"right_children":[2,4,-1,-1,-1],"split_conditions":[1.348399E-1,-6.3240025E-3,-1.2362931E-2,1.0982944E-2,-2.7893803E-3],"split_indices":[42,4,0,0,0],"split_type":[0,0,0,0,0],"sum_hessian":[4.926431E0,2.9465826E0,1.9798487E0,1.709559E0,1.2370236E0],"tree_param":{"num_deleted":"0","num_feature":"53","num_nodes":"5","size_leaf_vector":"0"}},{"base_weights":[5.27695E-1,1.0143143E0,-3.1130555E-1,1.2641014E0,1.5129493E-1,-6.9136155E-1,2.0832127E-1],"categories":[],"categories_nodes":[],"categories_segments":[],"categories_sizes":[],"default_left":[1,1,1,0,0,0,0],"id":39,"left_children":[1,3,5,-1,-1,-1,-1],"loss_changes":[3.341694E0,8.705826E-1,8.324355E-1,0E0,0E0,0E0,0E0],"parents":[2147483647,0,0,1,1,2,2],"right_children":[2,4,6,-1,-1,-1,-1],"split_conditions":[-2.5499767E-1,1.4163375E-1,2.211287E-1,1.2641014E-2,1.5129492E-3,-6.9136154E-3,2.0832126E-3],"split_indices":[31,28,12,0,0,0,0],"split_type":[0,0,0,0,0,0,0],"sum_hessian":[6.4115276E0,3.9256818E0,2.485846E0,2.6840763E0,1.2416056E0,1.2448583E0,1.2409878E0],"tree_param":{"num_deleted":"0","num_feature":"53","num_nodes":"7","size_leaf_vector":"0"}},{"base_weights":[3.7421823E-1,8.6424834E-1,-5.986751E-1,-9.260826E-2,1.2732067E0],"categories":[],"categories_nodes":[],"categories_segments":[],"categories_sizes":[],"default_left":[1,1,0,0,0],"id":40,"left_children":[1,3,-1,-1,-1],"loss_changes":[3.928568E0,2.1400678E0,0E0,0E0,0E0],"parents":[2147483647,0,0,1,1],"right_children":[2,4,-1,-1,-1],"split_conditions":[5.928108E-2,-2.4161121E-1,-5.9867506E-3,-9.2608255E-4,1.2732067E-2],"split_indices":[39,34,0,0,0],"split_type":[0,0,0,0,0],"sum_hessian":[6.1550827E0,4.167603E0,1.9874799E0,1.4795023E0,2.6881006E0],"tree_param":{"num_deleted":"0","num_feature":"53","num_nodes":"5","size_leaf_vector":"0"}},{"base_weights":[7.8918554E-2,4.9616528E-1,-7.828366E-1,-2.2464913E-1,9.540878E-1],"categories":[],"categories_nodes":[],"categories_segments":[],"categories_sizes":[],"default_left":[1,1,0,0,0],"id":41,"left_children":[1,3,-1,-1,-1],"loss_changes":[2.702881E0,1.8478994E0,0E0,0E0,0E0],"parents":[2147483647,0,0,1,1],"right_children":[2,4,-1,-1,-1],"split_conditions":[1.957709E-1,-2.5175145E-1,-7.828366E-3,-2.2464914E-3,9.540877E-3],"split_indices":[2,2,0,0,0],"split_type":[0,0,0,0,0],"sum_hessian":[5.436855E0,3.9490385E0,1.4878165E0,1.7320464E0,2.2169921E0],"tree_param":{"num_deleted":"0","num_feature":"53","num_nodes":"5","size_leaf_vector":"0"}},{"base_weights":[1.3188589E-1,6.230447E-1,-8.1305283E-1,1.0337722E0,-4.407839E-1,-1.0514351E0,-2.0787625E-1,9.296917E-2,1.3187242E0],"categories":[],"categories_nodes":[],"categories_segments":[],"categories_sizes":[],"default_left":[1,1,1,1,0,0,0,0,0],"id":42,"left_children":[1,3,5,7,-1,-1,-1,-1,-1],"loss_changes":[4.627232E0,3.2556713E0,2.820816E-1,1.1969419E0,0E0,0E0,0E0,0E0,0E0],"parents":[2147483647,0,0,1,1,2,2,3,3],"right_children":[2,4,6,8,-1,-1,-1,-1,-1],"split_conditions":[8.820863E-2,2.2910964E-1,-1.02930605E-1,-4.015904E-1,-4.407839E-3,-1.0514351E-2,-2.0787625E-3,9.296917E-4,1.3187241E-2],"split_indices":[3,2,2,15,0,0,0,0,0],"split_type":[0,0,0,0,0,0,0,0,0],"sum_hessian":[7.8785405E0,5.4081507E0,2.4703898E0,3.9221306E0,1.4860202E0,1.2432607E0,1.2271291E0,1.2200967E0,2.7020338E0],"tree_param":{"num_deleted":"0","num_feature":"53","num_nodes":"9","size_leaf_vector":"0"}},{"base_weights":[-1.8346411E-1,4.8793283E-1,-1.0855615E0,1.1699557E0,-3.5083628E-1],"categories":[],"categories_nodes":[],"categories_segments":[],"categories_sizes":[],"default_left":[1,1,0,0,0],"id":43,"left_children":[1,3,-1,-1,-1],"loss_changes":[5.024076E0,3.2388353E0,0E0,0E0,0E0],"parents":[2147483647,0,0,1,1],"right_children":[2,4,-1,-1,-1],"split_conditions":[-2.848797E-2,1.6293144E-1,-1.0855615E-2,1.1699557E-2,-3.5083627E-3],"split_indices":[4,42,0,0,0],"split_type":[0,0,0,0,0],"sum_hessian":[6.4205894E0,3.9441907E0,2.476399E0,1.9575844E0,1.9866064E0],"tree_param":{"num_deleted":"0","num_feature":"53","num_nodes":"5","size_leaf_vector":"0"}},{"base_weights":[3.1049052E-1,8.222418E-1,-7.233981E-1,-2.589206E-1,1.3325782E0],"categories":[],"categories_nodes":[],"categories_segments":[],"categories_sizes":[],"default_left":[1,1,0,0,0],"id":44,"left_children":[1,3,-1,-1,-1],"loss_changes":[4.888016E0,3.5980296E0,0E0,0E0,0E0],"parents":[2147483647,0,0,1,1],"right_children":[2,4,-1,-1,-1],"split_conditions":[8.820863E-2,-6.7200236E-2,-7.2339806E-3,-2.589206E-3,1.3325782E-2],"split_indices":[3,20,0,0,0],"split_type":[0,0,0,0,0],"sum_hessian":[7.1142673E0,4.8957114E0,2.218556E0,1.7278527E0,3.1678588E0],"tree_param":{"num_deleted":"0","num_feature":"53","num_nodes":"5","size_leaf_vector":"0"}},{"base_weights":[5.958873E-1,1.0949054E0,-7.2664034E-1,1.1550783E-1,1.3531374E0],"categories":[],"categories_nodes":[],"categories_segments":[],"categories_sizes":[],"default_left":[1,1,0,0,0],"id":45,"left_children":[1,3,-1,-1,-1],"loss_changes":[5.3460255E0,1.210681E0,0E0,0E0,0E0],"parents":[2147483647,0,0,1,1],"right_children":[2,4,-1,-1,-1],"split_conditions":[3.4649348E-1,-5.7291925E-1,-7.266403E-3,1.1550783E-3,1.3531374E-2],"split_indices":[16,8,0,0,0],"split_type":[0,0,0,0,0],"sum_hessian":[5.8949437E0,4.404967E0,1.4899771E0,1.2210784E0,3.1838882E0],"tree_param":{"num_deleted":"0","num_feature":"53","num_nodes":"5","size_leaf_vector":"0"}},{"base_weights":[8.343362E-2,8.1994367E-1,-7.7263975E-1,9.325605E-2,1.1119386E0,-1.5764472E-1,-1.0427395E0],"categories":[],"categories_nodes":[],"categories_segments":[],"categories_sizes":[],"default_left":[1,1,1,0,0,0,0],"id":46,"left_children":[1,3,5,-1,-1,-1,-1],"loss_changes":[4.676536E0,7.3063564E-1,4.137323E-1,0E0,0E0,0E0,0E0],"parents":[2147483647,0,0,1,1,2,2],"right_children":[2,4,6,-1,-1,-1,-1],"split_conditions":[1.1435409E-1,-2.852685E-1,-7.583091E-2,9.325605E-4,1.1119385E-2,-1.5764472E-3,-1.0427395E-2],"split_indices":[34,32,21,0,0,0,0],"split_type":[0,0,0,0,0,0,0],"sum_hessian":[5.4123273E0,2.9320152E0,2.4803119E0,1.2186177E0,1.7133975E0,1.2401792E0,1.2401327E0],"tree_param":{"num_deleted":"0","num_feature":"53","num_nodes":"7","size_leaf_vector":"0"}},{"base_weights":[3.1649578E-1,6.145635E-1,-6.743166E-1,9.864495E-1,-3.6205244E-1,7.4748E-2,1.2678958E0],"categories":[],"categories_nodes":[],"categories_segments":[],"categories_sizes":[],"default_left":[1,1,0,1,0,0,0],"id":47,"left_children":[1,3,-1,5,-1,-1,-1],"loss_changes":[2.670534E0,2.6800528E0,0E0,1.162672E0,0E0,0E0,0E0],"parents":[2147483647,0,0,1,1,3,3],"right_children":[2,4,-1,6,-1,-1,-1],"split_conditions":[3.9342058E-1,3.9618385E-1,-6.7431657E-3,-3.120439E-1,-3.6205244E-3,7.4748E-4,1.2678958E-2],"split_indices":[18,31,0,25,0,0,0],"split_type":[0,0,0,0,0,0,0],"sum_hessian":[6.6393504E0,5.395847E0,1.2435038E0,3.9005034E0,1.4953432E0,1.2186055E0,2.6818979E0],"tree_param":{"num_deleted":"0","num_feature":"53","num_nodes":"7","size_leaf_vector":"0"}},{"base_weights":[5.8640224E-1,1.1704615E0,-7.096999E-1,2.818317E-1,1.3905773E0],"categories":[],"categories_nodes":[],"categories_segments":[],"categories_sizes":[],"default_left":[1,1,0,0,0],"id":48,"left_children":[1,3,-1,-1,-1],"loss_changes":[7.1569195E0,8.0877495E-1,0E0,0E0,0E0],"parents":[2147483647,0,0,1,1],"right_children":[2,4,-1,-1,-1],"split_conditions":[4.0232897E-1,-2.0551965E-1,-7.0969993E-3,2.8183172E-3,1.3905773E-2],"split_indices":[4,20,0,0,0],"split_type":[0,0,0,0,0],"sum_hessian":[7.356986E0,5.1384134E0,2.218573E0,1.4728295E0,3.6655836E0],"tree_param":{"num_deleted":"0","num_feature":"53","num_nodes":"5","size_leaf_vector":"0"}},{"base_weights":[1.3404253E-1,1.0023793E0,-7.035313E-1,-1.0990072E0,-2.4812657E-2],"categories":[],"categories_nodes":[],"categories_segments":[],"categories_sizes":[],"default_left":[1,0,1,0,0],"id":49,"left_children":[1,-1,3,-1,-1],"loss_changes":[5.5411468E0,0E0,1.0389224E0,0E0,0E0],"parents":[2147483647,0,0,2,2],"right_children":[2,-1,4,-1,-1],"split_conditions":[-1.5738286E-1,1.0023793E-2,2.9016089E-2,-1.0990072E-2,-2.4812657E-4],"split_indices":[31,0,1,0,0],"split_type":[0,0,0,0,0],"sum_hessian":[5.6492057E0,2.677058E0,2.972148E0,1.4866614E0,1.4854865E0],"tree_param":{"num_deleted":"0","num_feature":"53","num_nodes":"5","size_leaf_vector":"0"}},{"base_weights":[-6.309211E-2,4.7617784E-1,-5.867476E-1,-6.860302E-1,1.1942502E0,2.7979684E-1,-1.1580931E0],"categories":[],"categories_nodes":[],"categories_segments":[],"categories_sizes":[],"default_left":[1,1,1,0,0,0,0],"id":50,"left_children":[1,3,5,-1,-1,-1,-1],"loss_changes":[2.3712509E0,4.325586E0,2.406512E0,0E0,0E0,0E0,0E0],"parents":[2147483647,0,0,1,1,2,2],"right_children":[2,4,6,-1,-1,-1,-1],"split_conditions":[9.492395E-3,-3.1798464E-1,1.2567976E-1,-6.860302E-3,1.1942502E-2,2.7979682E-3,-1.1580931E-2],"split_indices":[4,15,35,0,0,0,0],"split_type":[0,0,0,0,0,0,0],"sum_hessian":[6.407636E0,3.2014205E0,3.2062156E0,1.2396524E0,1.9617683E0,1.4767511E0,1.7294645E0],"tree_param":{"num_deleted":"0","num_feature":"53","num_nodes":"7","size_leaf_vector":"0"}},{"base_weights":[1.8995464E-1,6.163684E-1,-8.737416E-1,-6.5721714E-1,1.050681E0,1.3579379E-1,1.3004576E0],"categories":[],"categories_nodes":[],"categories_segments":[],"categories_sizes":[],"default_left":[1,1,0,0,1,0,0],"id":51,"left_children":[1,3,-1,-1,5,-1,-1],"loss_changes":[4.2138586E0,4.2143106E0,0E0,0E0,9.9692774E-1,0E0,0E0],"parents":[2147483647,0,0,1,1,4,4],"right_children":[2,4,-1,-1,6,-1,-1],"split_conditions":[2.8654975E-1,-2.9357967E-1,-8.737416E-3,-6.572171E-3,-2.8813463E-1,1.3579378E-3,1.3004576E-2],"split_indices":[18,2,0,0,18,0,0],"split_type":[0,0,0,0,0,0,0],"sum_hessian":[7.10299E0,5.370578E0,1.7324123E0,1.2352053E0,4.135372E0,1.2179391E0,2.9174333E0],"tree_param":{"num_deleted":"0","num_feature":"53","num_nodes":"7","size_leaf_vector":"0"}},{"base_weights":[2.9481712E-1,1.0333201E0,-5.097052E-1,-1.1619095E0,3.597453E-1],"categories":[],"categories_nodes":[],"categories_segments":[],"categories_sizes":[],"default_left":[1,0,1,0,0],"id":52,"left_children":[1,-1,3,-1,-1],"loss_changes":[4.595187E0,0E0,2.6561875E0,0E0,0E0],"parents":[2147483647,0,0,2,2],"right_children":[2,-1,4,-1,-1],"split_conditions":[-5.6178235E-2,1.0333201E-2,-1.17202684E-1,-1.1619095E-2,3.5974528E-3],"split_indices":[30,0,0,0,0],"split_type":[0,0,0,0,0],"sum_hessian":[5.8476853E0,2.9006624E0,2.947023E0,1.4916862E0,1.4553367E0],"tree_param":{"num_deleted":"0","num_feature":"53","num_nodes":"5","size_leaf_vector":"0"}},{"base_weights":[4.211002E-1,8.7885094E-1,-7.412001E-1,1.1751804E0,2.4476883E-1],"categories":[],"categories_nodes":[],"categories_segments":[],"categories_sizes":[],"default_left":[1,1,0,0,0],"id":53,"left_children":[1,3,-1,-1,-1],"loss_changes":[4.293319E0,7.210865E-1,0E0,0E0,0E0],"parents":[2147483647,0,0,1,1],"right_children":[2,4,-1,-1,-1],"split_conditions":[3.3899665E-1,-1.8005279E-1,-7.4120006E-3,1.17518045E-2,2.4476883E-3],"split_indices":[48,31,0,0,0],"split_type":[0,0,0,0,0],"sum_hessian":[5.845141E0,4.3685403E0,1.4766006E0,2.3956225E0,1.9729178E0],"tree_param":{"num_deleted":"0","num_feature":"53","num_nodes":"5","size_leaf_vector":"0"}},{"base_weights":[1.1911214E-1,-7.2723174E-1,9.023091E-1,-1.2061754E0,2.3522997E-1,1.185355E0,9.140947E-2],"categories":[],"categories_nodes":[],"categories_segments":[],"categories_sizes":[],"default_left":[1,1,1,0,0,0,0],"id":54,"left_children":[1,3,5,-1,-1,-1,-1],"loss_changes":[5.699757E0,2.2247264E0,9.0111685E-1,0E0,0E0,0E0,0E0],"parents":[2147483647,0,0,1,1,2,2],"right_children":[2,4,6,-1,-1,-1,-1],"split_conditions":[-5.9690323E-2,6.2388176E-1,2.118763E-1,-1.2061754E-2,2.3522996E-3,1.185355E-2,9.140947E-4],"split_indices":[26,40,26,0,0,0,0],"split_type":[0,0,0,0,0,0,0],"sum_hessian":[6.608869E0,3.2107275E0,3.3981416E0,1.9748007E0,1.2359267E0,2.1766136E0,1.221528E0],"tree_param":{"num_deleted":"0","num_feature":"53","num_nodes":"7","size_leaf_vector":"0"}},{"base_weights":[2.2151762E-1,7.727914E-1,-1.1869471E0,1.159491E0,-2.0442015E-1],"categories":[],"categories_nodes":[],"categories_segments":[],"categories_sizes":[],"default_left":[1,1,0,0,0],"id":55,"left_children":[1,3,-1,-1,-1],"loss_changes":[7.3705916E0,2.723152E0,0E0,0E0,0E0],"parents":[2147483647,0,0,1,1],"right_children":[2,4,-1,-1,-1],"split_conditions":[4.4669506E-1,8.820863E-2,-1.1869471E-2,1.1594909E-2,-2.0442014E-3],"split_indices":[48,3,0,0,0],"split_type":[0,0,0,0,0],"sum_hessian":[7.31133E0,5.5790215E0,1.7323081E0,3.8635983E0,1.7154232E0],"tree_param":{"num_deleted":"0","num_feature":"53","num_nodes":"5","size_leaf_vector":"0"}},{"base_weights":[5.4117728E-2,8.871692E-1,-5.2555996E-1,-9.322543E-1,1.14229895E-1],"categories":[],"categories_nodes":[],"categories_segments":[],"categories_sizes":[],"default_left":[1,0,1,0,0],"id":56,"left_children":[1,-1,3,-1,-1],"loss_changes":[3.7850997E0,0E0,1.3243909E0,0E0,0E0],"parents":[2147483647,0,0,2,2],"right_children":[2,-1,4,-1,-1],"split_conditions":[-4.2951906E-1,8.871691E-3,4.9522936E-2,-9.322543E-3,1.1422989E-3],"split_indices":[48,0,32,0,0],"split_type":[0,0,0,0,0],"sum_hessian":[5.8727064E0,2.192059E0,3.6806476E0,1.9707671E0,1.7098806E0],"tree_param":{"num_deleted":"0","num_feature":"53","num_nodes":"5","size_leaf_vector":"0"}},{"base_weights":[1.6851053E-1,9.0988886E-1,-8.0072916E-1,6.310907E-2,1.1938313E0,-1.4110814E-1,-1.0712054E0],"categories":[],"categories_nodes":[],"categories_segments":[],"categories_sizes":[],"default_left":[1,1,1,0,0,0,0],"id":57,"left_children":[1,3,5,-1,-1,-1,-1],"loss_changes":[5.9928503E0,1.0352416E0,5.102143E-1,0E0,0E0,0E0,0E0],"parents":[2147483647,0,0,1,1,2,2],"right_children":[2,4,6,-1,-1,-1,-1],"split_conditions":[1.1458213E-1,-4.6382168E-1,5.221318E-1,6.3109066E-4,1.1938313E-2,-1.4110814E-3,-1.0712054E-2],"split_indices":[31,14,31,0,0,0,0],"split_type":[0,0,0,0,0,0,0],"sum_hessian":[6.3260107E0,3.6190262E0,2.7069845E0,1.2157245E0,2.4033017E0,1.2297202E0,1.4772643E0],"tree_param":{"num_deleted":"0","num_feature":"53","num_nodes":"7","size_leaf_vector":"0"}},{"base_weights":[1.7864954E-1,7.120217E-1,-5.512769E-1,1.1550443E0,-2.3174529E-1,-1.0468237E0,1.9646068E-1],"categories":[],"categories_nodes":[],"categories_segments":[],"categories_sizes":[],"default_left":[1,1,1,0,0,0,0],"id":58,"left_children":[1,3,5,-1,-1,-1,-1],"loss_changes":[3.0640726E0,2.1078768E0,1.4880291E0,0E0,0E0,0E0,0E0],"parents":[2147483647,0,0,1,1,2,2],"right_children":[2,4,6,-1,-1,-1,-1],"split_conditions":[8.523224E-3,1.6293144E-1,1.7309384E-1,1.1550443E-2,-2.3174528E-3,-1.0468237E-2,1.9646068E-3],"split_indices":[4,42,38,0,0,0,0],"split_type":[0,0,0,0,0,0,0],"sum_hessian":[5.862055E0,3.4012334E0,2.4608212E0,2.1623285E0,1.2389051E0,1.2394286E0,1.2213925E0],"tree_param":{"num_deleted":"0","num_feature":"53","num_nodes":"7","size_leaf_vector":"0"}},{"base_weights":[9.0196244E-2,8.709674E-1,-7.444923E-1,1.1370039E0,1.0357817E-1,1.7505044E-1,-1.1864235E0],"categories":[],"categories_nodes":[],"categories_segments":[],"categories_sizes":[],"default_left":[1,1,1,0,0,0,0],"id":59,"left_children":[1,3,5,-1,-1,-1,-1],"loss_changes":[5.5925107E0,7.765608E-1,1.9167976E0,0E0,0E0,0E0,0E0],"parents":[2147483647,0,0,1,1,2,2],"right_children":[2,4,6,-1,-1,-1,-1],"split_conditions":[8.751687E-2,3.0305102E-1,-4.2573284E-2,1.1370039E-2,1.0357817E-3,1.7505044E-3,-1.1864235E-2],"split_indices":[31,18,17,0,0,0,0],"split_type":[0,0,0,0,0,0,0],"sum_hessian":[6.586431E0,3.380672E0,3.2057588E0,2.1527205E0,1.2279516E0,1.2366052E0,1.9691536E0],"tree_param":{"num_deleted":"0","num_feature":"53","num_nodes":"7","size_leaf_vector":"0"}},{"base_weights":[2.5664937E-1,7.237502E-1,-7.627121E-1,1.1950763E0,-6.2233504E-2],"categories":[],"categories_nodes":[],"categories_segments":[],"categories_sizes":[],"default_left":[1,1,0,0,0],"id":60,"left_children":[1,3,-1,-1,-1],"loss_changes":[3.9239576E0,2.0635386E0,0E0,0E0,0E0],"parents":[2147483647,0,0,1,1],"right_children":[2,4,-1,-1,-1],"split_conditions":[6.3618803E-1,1.0110151E-1,-7.627121E-3,1.1950763E-2,-6.22335E-4],"split_indices":[29,50,0,0,0],"split_type":[0,0,0,0,0],"sum_hessian":[6.0817666E0,4.369522E0,1.7122444E0,2.4061532E0,1.9633689E0],"tree_param":{"num_deleted":"0","num_feature":"53","num_nodes":"5","size_leaf_vector":"0"}},{"base_weights":[-3.671993E-2,6.2645423E-1,-1.0782772E0,1.1270283E0,-6.8204993E-1],"categories":[],"categories_nodes":[],"categories_segments":[],"categories_sizes":[],"default_left":[1,1,0,0,0],"id":61,"left_children":[1,3,-1,-1,-1],"loss_changes":[6.570237E0,4.598262E0,0E0,0E0,0E0],"parents":[2147483647,0,0,1,1],"right_children":[2,4,-1,-1,-1],"split_conditions":[8.820863E-2,3.0533755E-1,-1.0782772E-2,1.1270283E-2,-6.820499E-3],"split_indices":[3,18,0,0,0],"split_type":[0,0,0,0,0],"sum_hessian":[7.5340333E0,4.8466463E0,2.6873868E0,3.6058877E0,1.2407589E0],"tree_param":{"num_deleted":"0","num_feature":"53","num_nodes":"5","size_leaf_vector":"0"}},{"base_weights":[8.6797945E-2,9.484807E-1,-5.6599486E-1,7.46051E-2,-1.1156061E0],"categories":[],"categories_nodes":[],"categories_segments":[],"categories_sizes":[],"default_left":[1,0,1,0,0],"id":62,"left_children":[1,-1,3,-1,-1],"loss_changes":[4.78346E0,0E0,1.8160677E0,0E0,0E0],"parents":[2147483647,0,0,2,2],"right_children":[2,-1,4,-1,-1],"split_conditions":[-2.5499767E-1,9.484807E-3,1.104036E-1,7.4605097E-4,-1.1156061E-2],"split_indices":[31,0,4,0,0],"split_type":[0,0,0,0,0],"sum_hessian":[6.5495515E0,2.6278484E0,3.921703E0,2.2100432E0,1.7116599E0],"tree_param":{"num_deleted":"0","num_feature":"53","num_nodes":"5","size_leaf_vector":"0"}},{"base_weights":[-3.7400857E-2,7.9043496E-1,-7.160035E-1,5.0552677E-2,1.0770062E0,-1.2755275E0,2.1203186E-1],"categories":[],"categories_nodes":[],"categories_segments":[],"categories_sizes":[],"default_left":[1,1,1,0,0,0,0],"id":63,"left_children":[1,3,5,-1,-1,-1,-1],"loss_changes":[5.0760765E0,8.131411E-1,2.8338015E0,0E0,0E0,0E0,0E0],"parents":[2147483647,0,0,1,1,2,2],"right_children":[2,4,6,-1,-1,-1,-1],"split_conditions":[-4.8187755E-2,-2.272489E-1,2.3356563E-1,5.055268E-4,1.0770062E-2,-1.2755275E-2,2.1203186E-3],"split_indices":[30,30,30,0,0,0,0],"split_type":[0,0,0,0,0,0,0],"sum_hessian":[7.0283923E0,3.0918312E0,3.936561E0,1.1916311E0,1.9002001E0,2.2222817E0,1.7142793E0],"tree_param":{"num_deleted":"0","num_feature":"53","num_nodes":"7","size_leaf_vector":"0"}},{"base_weights":[-2.9541308E-1,1.0399137E0,-1.0510339E0,-2.722524E-1,-1.2505621E0],"categories":[],"categories_nodes":[],"categories_segments":[],"categories_sizes":[],"default_left":[1,0,1,0,0],"id":64,"left_children":[1,-1,3,-1,-1],"loss_changes":[7.6976123E0,0E0,3.863759E-1,0E0,0E0],"parents":[2147483647,0,0,2,2],"right_children":[2,-1,4,-1,-1],"split_conditions":[-1.5738286E-1,1.0399137E-2,-1.19450256E-1,-2.722524E-3,-1.2505621E-2],"split_indices":[31,0,48,0,0],"split_type":[0,0,0,0,0],"sum_hessian":[5.5457125E0,1.8681306E0,3.677582E0,1.2322909E0,2.4452913E0],"tree_param":{"num_deleted":"0","num_feature":"53","num_nodes":"5","size_leaf_vector":"0"}},{"base_weights":[5.336725E-2,9.502584E-1,-8.51818E-1,-2.4431771E-1,-1.0463909E0],"categories":[],"categories_nodes":[],"categories_segments":[],"categories_sizes":[],"default_left":[1,0,1,0,0],"id":65,"left_children":[1,-1,3,-1,-1],"loss_changes":[5.9178987E0,0E0,1.7685366E-1,0E0,0E0],"parents":[2147483647,0,0,2,2],"right_children":[2,-1,4,-1,-1],"split_conditions":[-1.3143617E-1,9.502583E-3,-1.4118056E-1,-2.4431772E-3,-1.0463908E-2],"split_indices":[48,0,11,0,0],"split_type":[0,0,0,0,0],"sum_hessian":[5.2923384E0,2.6333365E0,2.6590018E0,1.1922355E0,1.4667665E0],"tree_param":{"num_deleted":"0","num_feature":"53","num_nodes":"5","size_leaf_vector":"0"}},{"base_weights":[1.59223E-1,8.3131E-1,-6.0279745E-1],"categories":[],"categories_nodes":[],"categories_segments":[],"categories_sizes":[],"default_left":[1,0,0],"id":66,"left_children":[1,-1,-1],"loss_changes":[3.1115663E0,0E0,0E0],"parents":[2147483647,0,0],"right_children":[2,-1,-1],"split_conditions":[9.835443E-2,8.3131E-3,-6.027974E-3],"split_indices":[34,0,0],"split_type":[0,0,0],"sum_hessian":[4.097111E0,2.128706E0,1.9684051E0],"tree_param":{"num_deleted":"0","num_feature":"53","num_nodes":"3","size_leaf_vector":"0"}},{"base_weights":[2.8397113E-1,9.180062E-1,-4.3027064E-1,4.4716142E-2,1.1969924E0,3.2025784E-1,-1.0966249E0],"categories":[],"categories_nodes":[],"categories_segments":[],"categories_sizes":[],"default_left":[1,1,1,0,0,0,0],"id":67,"left_children":[1,3,5,-1,-1,-1,-1],"loss_changes":[4.2416368E0,1.1205306E0,2.6894195E0,0E0,0E0,0E0,0E0],"parents":[2147483647,0,0,1,1,2,2],"right_children":[2,4,6,-1,-1,-1,-1],"split_conditions":[1.1458213E-1,-5.0473183E-2,1.5442848E-2,4.471614E-4,1.1969924E-2,3.2025783E-3,-1.0966248E-2],"split_indices":[31,21,4,0,0,0,0],"split_type":[0,0,0,0,0,0,0],"sum_hessian":[7.4942236E0,3.8188918E0,3.6753318E0,1.2055447E0,2.613347E0,1.9727598E0,1.702572E0],"tree_param":{"num_deleted":"0","num_feature":"53","num_nodes":"7","size_leaf_vector":"0"}},{"base_weights":[2.3053876E-1,9.153504E-1,-5.5167866E-1,-1.0119351E0,1.6082215E-1],"categories":[],"categories_nodes":[],"categories_segments":[],"categories_sizes":[],"default_left":[1,0,1,0,0],"id":68,"left_children":[1,-1,3,-1,-1],"loss_changes":[3.738335E0,0E0,1.2913564E0,0E0,0E0],"parents":[2147483647,0,0,2,2],"right_children":[2,-1,4,-1,-1],"split_conditions":[8.650267E-2,9.153504E-3,1.9161963E-1,-1.0119351E-2,1.6082214E-3],"split_indices":[42,0,42,0,0],"split_type":[0,0,0,0,0],"sum_hessian":[5.036079E0,2.5944788E0,2.4416E0,1.2280527E0,1.2135475E0],"tree_param":{"num_deleted":"0","num_feature":"53","num_nodes":"5","size_leaf_vector":"0"}},{"base_weights":[7.8128606E-2,5.580843E-1,-9.259781E-1,1.1046178E0,-6.816903E-1],"categories":[],"categories_nodes":[],"categories_segments":[],"categories_sizes":[],"default_left":[1,1,0,0,0],"id":69,"left_children":[1,3,-1,-1,-1],"loss_changes":[4.377039E0,4.847955E0,0E0,0E0,0E0],"parents":[2147483647,0,0,1,1],"right_children":[2,4,-1,-1,-1],"split_conditions":[3.3739513E-1,7.725548E-2,-9.259781E-3,1.1046178E-2,-6.8169027E-3],"split_indices":[1,3,0,0,0],"split_type":[0,0,0,0,0],"sum_hessian":[7.0100646E0,5.043504E0,1.9665602E0,3.5760715E0,1.467433E0],"tree_param":{"num_deleted":"0","num_feature":"53","num_nodes":"5","size_leaf_vector":"0"}},{"base_weights":[5.1497376E-1,1.2267197E0,-7.327194E-1],"categories":[],"categories_nodes":[],"categories_segments":[],"categories_sizes":[],"default_left":[1,0,0],"id":70,"left_children":[1,-1,-1],"loss_changes":[5.423372E0,0E0,0E0],"parents":[2147483647,0,0],"right_children":[2,-1,-1],"split_conditions":[4.986531E-2,1.22671975E-2,-7.327194E-3],"split_indices":[4,0,0],"split_type":[0,0,0],"sum_hessian":[4.0949593E0,2.6182117E0,1.4767476E0],"tree_param":{"num_deleted":"0","num_feature":"53","num_nodes":"3","size_leaf_vector":"0"}},{"base_weights":[4.486936E-1,1.0699824E0,-2.4631509E-1,4.8028648E-1,-8.8065094E-1],"categories":[],"categories_nodes":[],"categories_segments":[],"categories_sizes":[],"default_left":[1,0,1,0,0],"id":71,"left_children":[1,-1,3,-1,-1],"loss_changes":[3.9915793E0,0E0,2.675862E0,0E0,0E0],"parents":[2147483647,0,0,2,2],"right_children":[2,-1,4,-1,-1],"split_conditions":[-2.5499767E-1,1.06998235E-2,-2.4474379E-2,4.8028645E-3,-8.806509E-3],"split_indices":[31,0,48,0,0],"split_type":[0,0,0,0,0],"sum_hessian":[7.633665E0,3.7457263E0,3.887939E0,1.9253702E0,1.9625686E0],"tree_param":{"num_deleted":"0","num_feature":"53","num_nodes":"5","size_leaf_vector":"0"}},{"base_weights":[-4.0638614E-2,7.956528E-1,-6.9329584E-1,-1.9147694E-1,-9.937714E-1],"categories":[],"categories_nodes":[],"categories_segments":[],"categories_sizes":[],"default_left":[1,0,1,0,0],"id":72,"left_children":[1,-1,3,-1,-1],"loss_changes":[3.84882E0,0E0,4.018973E-1,0E0,0E0],"parents":[2147483647,0,0,2,2],"right_children":[2,-1,4,-1,-1],"split_conditions":[-3.012385E-1,7.956528E-3,-1.7679034E-1,-1.9147694E-3,-9.937714E-3],"split_indices":[31,0,10,0,0],"split_type":[0,0,0,0,0],"sum_hessian":[5.0409074E0,2.1135645E0,2.9273427E0,1.7095313E0,1.2178115E0],"tree_param":{"num_deleted":"0","num_feature":"53","num_nodes":"5","size_leaf_vector":"0"}},{"base_weights":[1.6766086E-1,7.7240115E-1,-8.8715994E-1,1.176335E0,-9.424122E-2],"categories":[],"categories_nodes":[],"categories_segments":[],"categories_sizes":[],"default_left":[1,1,0,0,0],"id":73,"left_children":[1,3,-1,-1,-1],"loss_changes":[4.9979534E0,1.8023093E0,0E0,0E0,0E0],"parents":[2147483647,0,0,1,1],"right_children":[2,4,-1,-1,-1],"split_conditions":[1.1137165E-1,-8.120406E-3,-8.871599E-3,1.1763349E-2,-9.424121E-4],"split_indices":[4,50,0,0,0],"split_type":[0,0,0,0,0],"sum_hessian":[5.760872E0,3.8318005E0,1.9290713E0,2.369876E0,1.4619246E0],"tree_param":{"num_deleted":"0","num_feature":"53","num_nodes":"5","size_leaf_vector":"0"}},{"base_weights":[4.0384603E-1,8.658243E-1,-7.3371714E-1,2.6896402E-2,1.0811388E0],"categories":[],"categories_nodes":[],"categories_segments":[],"categories_sizes":[],"default_left":[1,1,0,0,0],"id":74,"left_children":[1,3,-1,-1,-1],"loss_changes":[4.543128E0,1.0090351E0,0E0,0E0,0E0],"parents":[2147483647,0,0,1,1],"right_children":[2,4,-1,-1,-1],"split_conditions":[2.3355728E-1,-2.628579E-1,-7.337171E-3,2.68964E-4,1.08113885E-2],"split_indices":[37,37,0,0,0],"split_type":[0,0,0,0,0],"sum_hessian":[6.43604E0,4.7470737E0,1.6889664E0,1.1992735E0,3.5478E0],"tree_param":{"num_deleted":"0","num_feature":"53","num_nodes":"5","size_leaf_vector":"0"}},{"base_weights":[1.5432239E-1,-6.6720885E-1,6.828822E-1,-2.319013E-1,1.1083115E0],"categories":[],"categories_nodes":[],"categories_segments":[],"categories_sizes":[],"default_left":[1,0,1,0,0],"id":75,"left_children":[1,-1,3,-1,-1],"loss_changes":[3.1783526E0,0E0,1.9342322E0,0E0,0E0],"parents":[2147483647,0,0,2,2],"right_children":[2,-1,4,-1,-1],"split_conditions":[-2.1562666E-1,-6.6720885E-3,-6.006258E-1,-2.319013E-3,1.1083115E-2],"split_indices":[20,0,38,0,0],"split_type":[0,0,0,0,0],"sum_hessian":[5.2702656E0,1.9606098E0,3.309656E0,1.1949986E0,2.1146572E0],"tree_param":{"num_deleted":"0","num_feature":"53","num_nodes":"5","size_leaf_vector":"0"}},{"base_weights":[1.0163927E-1,5.8486974E-1,-6.932822E-1,1.1163263E0,-2.7972353E-1],"categories":[],"categories_nodes":[],"categories_segments":[],"categories_sizes":[],"default_left":[1,1,0,0,0],"id":76,"left_children":[1,3,-1,-1,-1],"loss_changes":[3.1778433E0,2.623993E0,0E0,0E0,0E0],"parents":[2147483647,0,0,1,1],"right_children":[2,4,-1,-1,-1],"split_conditions":[8.820863E-2,7.472253E-2,-6.9328216E-3,1.1163263E-2,-2.7972353E-3],"split_indices":[3,41,0,0,0],"split_type":[0,0,0,0,0],"sum_hessian":[6.2172484E0,4.0310354E0,2.1862128E0,2.3161585E0,1.7148769E0],"tree_param":{"num_deleted":"0","num_feature":"53","num_nodes":"5","size_leaf_vector":"0"}},{"base_weights":[1.12583175E-1,9.169215E-1,-5.9769374E-1,-1.1764663E0,2.0711589E-1],"categories":[],"categories_nodes":[],"categories_segments":[],"categories_sizes":[],"default_left":[1,0,1,0,0],"id":77,"left_children":[1,-1,3,-1,-1],"loss_changes":[4.6668544E0,0E0,2.309032E0,0E0,0E0],"parents":[2147483647,0,0,2,2],"right_children":[2,-1,4,-1,-1],"split_conditions":[-1.5738286E-1,9.169214E-3,3.2763854E-1,-1.1764663E-2,2.0711587E-3],"split_indices":[31,0,12,0,0],"split_type":[0,0,0,0,0],"sum_hessian":[6.2095137E0,2.77551E0,3.4340038E0,1.7288909E0,1.7051129E0],"tree_param":{"num_deleted":"0","num_feature":"53","num_nodes":"5","size_leaf_vector":"0"}},{"base_weights":[2.884779E-1,9.248005E-1,-1.112473E0,1.2562362E0,-5.6264255E-2],"categories":[],"categories_nodes":[],"categories_segments":[],"categories_sizes":[],"default_left":[1,1,0,0,0],"id":78,"left_children":[1,3,-1,-1,-1],"loss_changes":[8.069054E0,2.0141025E0,0E0,0E0,0E0],"parents":[2147483647,0,0,1,1],"right_children":[2,4,-1,-1,-1],"split_conditions":[1.751906E-1,8.363527E-2,-1.112473E-2,1.2562362E-2,-5.626425E-4],"split_indices":[35,3,0,0,0],"split_type":[0,0,0,0,0],"sum_hessian":[6.8974524E0,4.9768195E0,1.920633E0,3.510407E0,1.4664123E0],"tree_param":{"num_deleted":"0","num_feature":"53","num_nodes":"5","size_leaf_vector":"0"}},{"base_weights":[2.8020895E-1,6.3871133E-1,-5.477936E-1,-8.0986485E-2,1.0590835E0],"categories":[],"categories_nodes":[],"categories_segments":[],"categories_sizes":[],"default_left":[1,1,0,0,0],"id":79,"left_children":[1,3,-1,-1,-1],"loss_changes":[2.7142935E0,1.9071393E0,0E0,0E0,0E0],"parents":[2147483647,0,0,1,1],"right_children":[2,4,-1,-1,-1],"split_conditions":[5.221318E-1,-4.015904E-1,-5.477936E-3,-8.0986484E-4,1.0590835E-2],"split_indices":[31,15,0,0,0],"split_type":[0,0,0,0,0],"sum_hessian":[6.9652486E0,5.020236E0,1.9450126E0,2.1487744E0,2.8714616E0],"tree_param":{"num_deleted":"0","num_feature":"53","num_nodes":"5","size_leaf_vector":"0"}},{"base_weights":[-1.21998906E-1,4.9531168E-1,-1.1840434E0,9.8016876E-1,-6.162388E-1],"categories":[],"categories_nodes":[],"categories_segments":[],"categories_sizes":[],"default_left":[1,1,0,0,0],"id":80,"left_children":[1,3,-1,-1,-1],"loss_changes":[5.3061132E0,3.4376154E0,0E0,0E0,0E0],"parents":[2147483647,0,0,1,1],"right_children":[2,4,-1,-1,-1],"split_conditions":[3.3899665E-1,8.045556E-2,-1.1840434E-2,9.801688E-3,-6.162388E-3],"split_indices":[48,3,0,0,0],"split_type":[0,0,0,0,0],"sum_hessian":[6.198842E0,4.2576933E0,1.9411488E0,3.0468552E0,1.2108382E0],"tree_param":{"num_deleted":"0","num_feature":"53","num_nodes":"5","size_leaf_vector":"0"}},{"base_weights":[1.4992645E-1,9.284828E-1,-1.0190344E0,1.1856415E0,5.8770172E-2],"categories":[],"categories_nodes":[],"categories_segments":[],"categories_sizes":[],"default_left":[1,1,0,0,0],"id":81,"left_children":[1,3,-1,-1,-1],"loss_changes":[7.693206E0,1.0425677E0,0E0,0E0,0E0],"parents":[2147483647,0,0,1,1],"right_children":[2,4,-1,-1,-1],"split_conditions":[1.7323303E-1,1.6998835E-1,-1.01903435E-2,1.1856415E-2,5.877017E-4],"split_indices":[42,41,0,0,0],"split_type":[0,0,0,0,0],"sum_hessian":[6.413511E0,3.9730694E0,2.4404411E0,2.786032E0,1.1870372E0],"tree_param":{"num_deleted":"0","num_feature":"53","num_nodes":"5","size_leaf_vector":"0"}},{"base_weights":[-7.306057E-2,8.968168E-1,-9.2951E-1,-2.2581455E-1,-1.1463394E0],"categories":[],"categories_nodes":[],"categories_segments":[],"categories_sizes":[],"default_left":[1,0,1,0,0],"id":82,"left_children":[1,-1,3,-1,-1],"loss_changes":[6.5532174E0,0E0,3.7400794E-1,0E0,0E0],"parents":[2147483647,0,0,2,2],"right_children":[2,-1,4,-1,-1],"split_conditions":[-2.5499767E-1,8.968168E-3,-1.2620696E-1,-2.2581455E-3,-1.1463393E-2],"split_indices":[31,0,19,0,0],"split_type":[0,0,0,0,0],"sum_hessian":[5.885706E0,2.7379777E0,3.1477282E0,1.2223071E0,1.9254212E0],"tree_param":{"num_deleted":"0","num_feature":"53","num_nodes":"5","size_leaf_vector":"0"}},{"base_weights":[2.4895684E-1,9.4606024E-1,-9.996297E-1],"categories":[],"categories_nodes":[],"categories_segments":[],"categories_sizes":[],"default_left":[1,0,0],"id":83,"left_children":[1,-1,-1],"loss_changes":[5.6634817E0,0E0,0E0],"parents":[2147483647,0,0],"right_children":[2,-1,-1],"split_conditions":[1.3482326E-1,9.460602E-3,-9.996297E-3],"split_indices":[22,0,0],"split_type":[0,0,0],"sum_hessian":[4.4202724E0,2.9920588E0,1.4282135E0],"tree_param":{"num_deleted":"0","num_feature":"53","num_nodes":"3","size_leaf_vector":"0"}},{"base_weights":[-1.5349022E-1,1.0162126E0,-9.1451395E-1,-1.7448707E-1,-1.1608458E0],"categories":[],"categories_nodes":[],"categories_segments":[],"categories_sizes":[],"default_left":[1,0,1,0,0],"id":84,"left_children":[1,-1,3,-1,-1],"loss_changes":[6.236635E0,0E0,5.518439E-1,0E0,0E0],"parents":[2147483647,0,0,2,2],"right_children":[2,-1,4,-1,-1],"split_conditions":[-1.5738286E-1,1.0162125E-2,-1.12910844E-1,-1.7448707E-3,-1.1608457E-2],"split_indices":[31,0,33,0,0],"split_type":[0,0,0,0,0],"sum_hessian":[4.962103E0,1.823712E0,3.138391E0,1.2104162E0,1.9279747E0],"tree_param":{"num_deleted":"0","num_feature":"53","num_nodes":"5","size_leaf_vector":"0"}},{"base_weights":[-6.983867E-2,8.519929E-1,-1.0074474E0,1.10886E0,8.231899E-2,-2.7747187E-1,-1.1956508E0],"categories":[],"categories_nodes":[],"categories_segments":[],"categories_sizes":[],"default_left":[1,1,1,0,0,0,0],"id":85,"left_children":[1,3,5,-1,-1,-1,-1],"loss_changes":[7.6425366E0,7.9832864E-1,2.6579142E-1,0E0,0E0,0E0,0E0],"parents":[2147483647,0,0,1,1,2,2],"right_children":[2,4,6,-1,-1,-1,-1],"split_conditions":[9.492395E-3,1.3792555E-1,-1.1755431E-1,1.1088599E-2,8.231899E-4,-2.7747187E-3,-1.1956508E-2],"split_indices":[4,42,19,0,0,0,0],"split_type":[0,0,0,0,0,0,0],"sum_hessian":[6.8491993E0,3.499701E0,3.3494985E0,2.2935686E0,1.2061323E0,1.1937349E0,2.1557636E0],"tree_param":{"num_deleted":"0","num_feature":"53","num_nodes":"7","size_leaf_vector":"0"}},{"base_weights":[4.3627626E-1,8.349902E-1,-6.3549364E-1,1.1430411E0,1.7319159E-1],"categories":[],"categories_nodes":[],"categories_segments":[],"categories_sizes":[],"default_left":[1,1,0,0,0],"id":86,"left_children":[1,3,-1,-1,-1],"loss_changes":[3.4611187E0,9.091215E-1,0E0,0E0,0E0],"parents":[2147483647,0,0,1,1],"right_children":[2,4,-1,-1,-1],"split_conditions":[1.751906E-1,-2.3110159E-2,-6.3549364E-3,1.1430411E-2,1.7319159E-3],"split_indices":[35,19,0,0,0],"split_type":[0,0,0,0,0],"sum_hessian":[5.857675E0,4.430419E0,1.4272561E0,2.5269926E0,1.9034265E0],"tree_param":{"num_deleted":"0","num_feature":"53","num_nodes":"5","size_leaf_vector":"0"}},{"base_weights":[2.704285E-1,9.315352E-1,-8.9302146E-1,1.1778884E0,6.6744596E-2],"categories":[],"categories_nodes":[],"categories_segments":[],"categories_sizes":[],"default_left":[1,1,0,0,0],"id":87,"left_children":[1,3,-1,-1,-1],"loss_changes":[6.5011287E0,1.0269594E0,0E0,0E0,0E0],"parents":[2147483647,0,0,1,1],"right_children":[2,4,-1,-1,-1],"split_conditions":[3.89906E-1,2.1823613E-1,-8.930215E-3,1.1778884E-2,6.6744594E-4],"split_indices":[31,48,0,0,0],"split_type":[0,0,0,0,0],"sum_hessian":[6.3706565E0,4.1894317E0,2.181225E0,2.9788072E0,1.2106246E0],"tree_param":{"num_deleted":"0","num_feature":"53","num_nodes":"5","size_leaf_vector":"0"}},{"base_weights":[-6.564706E-2,9.6114904E-1,-6.581006E-1,1.2633769E-1,-9.9265915E-1],"categories":[],"categories_nodes":[],"categories_segments":[],"categories_sizes":[],"default_left":[1,0,1,0,0],"id":88,"left_children":[1,-1,3,-1,-1],"loss_changes":[4.256787E0,0E0,1.272663E0,0E0,0E0],"parents":[2147483647,0,0,2,2],"right_children":[2,-1,4,-1,-1],"split_conditions":[-4.1297102E-1,9.61149E-3,-1.2466906E-1,1.2633769E-3,-9.926591E-3],"split_indices":[31,0,50,0,0],"split_type":[0,0,0,0,0],"sum_hessian":[4.9577208E0,1.586243E0,3.3714776E0,1.1940851E0,2.1773925E0],"tree_param":{"num_deleted":"0","num_feature":"53","num_nodes":"5","size_leaf_vector":"0"}},{"base_weights":[4.159607E-1,1.0323429E0,-4.204833E-1,-9.678956E-1,1.8931682E-1],"categories":[],"categories_nodes":[],"categories_segments":[],"categories_sizes":[],"default_left":[1,0,1,0,0],"id":89,"left_children":[1,-1,3,-1,-1],"loss_changes":[4.322595E0,0E0,1.4885944E0,0E0,0E0],"parents":[2147483647,0,0,2,2],"right_children":[2,-1,4,-1,-1],"split_conditions":[-9.409367E-3,1.0323429E-2,7.273898E-2,-9.678956E-3,1.8931682E-3],"split_indices":[39,0,51,0,0],"split_type":[0,0,0,0,0],"sum_hessian":[6.5421734E0,3.6317232E0,2.9104502E0,1.2242327E0,1.6862175E0],"tree_param":{"num_deleted":"0","num_feature":"53","num_nodes":"5","size_leaf_vector":"0"}},{"base_weights":[2.1010447E-1,9.42483E-1,-5.980635E-1,-1.0655986E0,2.3823267E-1],"categories":[],"categories_nodes":[],"categories_segments":[],"categories_sizes":[],"default_left":[1,0,1,0,0],"id":90,"left_children":[1,-1,3,-1,-1],"loss_changes":[4.614884E0,0E0,1.7653493E0,0E0,0E0],"parents":[2147483647,0,0,2,2],"right_children":[2,-1,4,-1,-1],"split_conditions":[3.3352603E-3,9.42483E-3,4.474349E-1,-1.0655986E-2,2.3823266E-3],"split_indices":[3,0,38,0,0],"split_type":[0,0,0,0,0],"sum_hessian":[5.8446064E0,2.9788835E0,2.8657227E0,1.6622478E0,1.2034748E0],"tree_param":{"num_deleted":"0","num_feature":"53","num_nodes":"5","size_leaf_vector":"0"}},{"base_weights":[-1.4898738E-1,6.365043E-1,-7.958685E-1,9.430721E-1,-2.3831395E-2,-1.1921167E0,2.5912367E-2],"categories":[],"categories_nodes":[],"categories_segments":[],"categories_sizes":[],"default_left":[1,1,1,0,0,0,0],"id":91,"left_children":[1,3,5,-1,-1,-1,-1],"loss_changes":[4.094221E0,7.804655E-1,1.436409E0,0E0,0E0,0E0,0E0],"parents":[2147483647,0,0,1,1,2,2],"right_children":[2,4,6,-1,-1,-1,-1],"split_conditions":[-7.779887E-3,1.8315408E-1,1.1978337E-1,9.4307205E-3,-2.3831395E-4,-1.1921167E-2,2.5912366E-4],"split_indices":[3,26,21,0,0,0,0],"split_type":[0,0,0,0,0,0,0],"sum_hessian":[6.060633E0,2.7443178E0,3.3163157E0,1.5817862E0,1.1625316E0,1.9334092E0,1.3829064E0],"tree_param":{"num_deleted":"0","num_feature":"53","num_nodes":"7","size_leaf_vector":"0"}},{"base_weights":[4.7773013E-1,9.1334337E-1,-7.5815517E-1,1.2139006E0,-1.2571476E-1],"categories":[],"categories_nodes":[],"categories_segments":[],"categories_sizes":[],"default_left":[1,1,0,0,0],"id":92,"left_children":[1,3,-1,-1,-1],"loss_changes":[4.6121325E0,1.9754195E0,0E0,0E0,0E0],"parents":[2147483647,0,0,1,1],"right_children":[2,4,-1,-1,-1],"split_conditions":[3.4687173E-1,3.89906E-1,-7.5815516E-3,1.2139006E-2,-1.2571476E-3],"split_indices":[48,31,0,0,0],"split_type":[0,0,0,0,0],"sum_hessian":[6.280664E0,4.8368106E0,1.4438531E0,3.6211033E0,1.2157075E0],"tree_param":{"num_deleted":"0","num_feature":"53","num_nodes":"5","size_leaf_vector":"0"}},{"base_weights":[2.9575724E-2,7.3831093E-1,-9.3562365E-1,1.0045775E0,5.598804E-2],"categories":[],"categories_nodes":[],"categories_segments":[],"categories_sizes":[],"default_left":[1,1,0,0,0],"id":93,"left_children":[1,3,-1,-1,-1],"loss_changes":[4.7337217E0,6.644323E-1,0E0,0E0,0E0],"parents":[2147483647,0,0,1,1],"right_children":[2,4,-1,-1,-1],"split_conditions":[9.492395E-3,-1.6861647E-2,-9.356236E-3,1.0045775E-2,5.598804E-4],"split_indices":[4,50,0,0,0],"split_type":[0,0,0,0,0],"sum_hessian":[4.91012E0,2.9667425E0,1.9433774E0,1.7942662E0,1.1724764E0],"tree_param":{"num_deleted":"0","num_feature":"53","num_nodes":"5","size_leaf_vector":"0"}},{"base_weights":[3.686E-1,7.2001404E-1,-6.569086E-1,-1.4284672E-1,1.1465763E0],"categories":[],"categories_nodes":[],"categories_segments":[],"categories_sizes":[],"default_left":[1,1,0,0,0],"id":94,"left_children":[1,3,-1,-1,-1],"loss_changes":[2.8554265E0,2.151627E0,0E0,0E0,0E0],"parents":[2147483647,0,0,1,1],"right_children":[2,4,-1,-1,-1],"split_conditions":[3.9342058E-1,-1.8571024E-1,-6.5690856E-3,-1.4284671E-3,1.1465763E-2],"split_indices":[18,9,0,0,0],"split_type":[0,0,0,0,0],"sum_hessian":[5.6109533E0,4.4008102E0,1.2101429E0,1.6758931E0,2.7249174E0],"tree_param":{"num_deleted":"0","num_feature":"53","num_nodes":"5","size_leaf_vector":"0"}},{"base_weights":[1.6145572E-1,7.140178E-1,-7.030194E-1,1.0849632E0,-1.7820704E-1],"categories":[],"categories_nodes":[],"categories_segments":[],"categories_sizes":[],"default_left":[1,1,0,0,0],"id":95,"left_children":[1,3,-1,-1,-1],"loss_changes":[3.7645266E0,1.7365983E0,0E0,0E0,0E0],"parents":[2147483647,0,0,1,1],"right_children":[2,4,-1,-1,-1],"split_conditions":[9.492395E-3,1.5060958E-1,-7.0301937E-3,1.0849631E-2,-1.7820704E-3],"split_indices":[4,42,0,0,0],"split_type":[0,0,0,0,0],"sum_hessian":[5.8300633E0,3.6628551E0,2.1672082E0,2.43463E0,1.2282254E0],"tree_param":{"num_deleted":"0","num_feature":"53","num_nodes":"5","size_leaf_vector":"0"}},{"base_weights":[7.866351E-2,9.4276834E-1,-7.106071E-1,1.878216E-1,-1.0609187E0],"categories":[],"categories_nodes":[],"categories_segments":[],"categories_sizes":[],"default_left":[1,0,1,0,0],"id":96,"left_children":[1,-1,3,-1,-1],"loss_changes":[6.254899E0,0E0,1.7257044E0,0E0,0E0],"parents":[2147483647,0,0,2,2],"right_children":[2,-1,4,-1,-1],"split_conditions":[-2.9929748E-1,9.427683E-3,-4.992036E-2,1.8782159E-3,-1.0609186E-2],"split_indices":[12,0,48,0,0],"split_type":[0,0,0,0,0],"sum_hessian":[7.1889415E0,3.3389406E0,3.8500006E0,1.2101715E0,2.6398292E0],"tree_param":{"num_deleted":"0","num_feature":"53","num_nodes":"5","size_leaf_vector":"0"}},{"base_weights":[3.9882478E-1,9.054941E-1,-4.4544184E-1,1.1452762E0,8.352337E-2,-9.3353903E-1,2.4890253E-1],"categories":[],"categories_nodes":[],"categories_segments":[],"categories_sizes":[],"default_left":[1,1,1,0,0,0,0],"id":97,"left_children":[1,3,5,-1,-1,-1,-1],"loss_changes":[3.51527E0,8.6540174E-1,1.3842099E0,0E0,0E0,0E0,0E0],"parents":[2147483647,0,0,1,1,2,2],"right_children":[2,4,6,-1,-1,-1,-1],"split_conditions":[1.3381565E-1,6.0141776E-2,1.347178E-2,1.14527615E-2,8.3523366E-4,-9.33539E-3,2.4890252E-3],"split_indices":[35,19,19,0,0,0,0],"split_type":[0,0,0,0,0,0,0],"sum_hessian":[6.2748647E0,3.8761506E0,2.3987138E0,2.6962745E0,1.1798762E0,1.2062658E0,1.192448E0],"tree_param":{"num_deleted":"0","num_feature":"53","num_nodes":"7","size_leaf_vector":"0"}},{"base_weights":[3.6770773E-1,7.4157065E-1,-7.168905E-1,-1.4671117E-1,1.2341709E0],"categories":[],"categories_nodes":[],"categories_segments":[],"categories_sizes":[],"default_left":[1,1,0,0,0],"id":98,"left_children":[1,3,-1,-1,-1],"loss_changes":[3.5681467E0,2.8329184E0,0E0,0E0,0E0],"parents":[2147483647,0,0,1,1],"right_children":[2,4,-1,-1,-1],"split_conditions":[1.1937471E-1,-3.6427563E-1,-7.168905E-3,-1.4671116E-3,1.2341709E-2],"split_indices":[4,14,0,0,0],"split_type":[0,0,0,0,0],"sum_hessian":[6.488506E0,5.0604362E0,1.4280696E0,2.055687E0,3.0047493E0],"tree_param":{"num_deleted":"0","num_feature":"53","num_nodes":"5","size_leaf_vector":"0"}},{"base_weights":[7.996549E-2,6.8928134E-1,-6.806256E-1,-1.1796223E-2,1.0037413E0],"categories":[],"categories_nodes":[],"categories_segments":[],"categories_sizes":[],"default_left":[1,1,0,0,0],"id":99,"left_children":[1,3,-1,-1,-1],"loss_changes":[3.1920571E0,8.405448E-1,0E0,0E0,0E0],"parents":[2147483647,0,0,1,1],"right_children":[2,4,-1,-1,-1],"split_conditions":[5.083448E-2,-4.0514153E-1,-6.8062562E-3,-1.1796223E-4,1.0037413E-2],"split_indices":[4,7,0,0,0],"split_type":[0,0,0,0,0],"sum_hessian":[4.875439E0,2.7589653E0,2.1164742E0,1.1523433E0,1.6066219E0],"tree_param":{"num_deleted":"0","num_feature":"53","num_nodes":"5","size_leaf_vector":"0"}},{"base_weights":[2.3224474E-1,8.5937804E-1,-5.36832E-1,1.1249816E0,-1.2090826E-2,-1.2137444E0,6.7261595E-1],"categories":[],"categories_nodes":[],"categories_segments":[],"categories_sizes":[],"default_left":[1,1,1,0,0,0,0],"id":100,"left_children":[1,3,5,-1,-1,-1,-1],"loss_changes":[4.5235353E0,1.176429E0,4.4174275E0,0E0,0E0,0E0,0E0],"parents":[2147483647,0,0,1,1,2,2],"right_children":[2,4,6,-1,-1,-1,-1],"split_conditions":[-1.5738286E-1,2.200222E-1,2.3204958E-1,1.1249816E-2,-1.2090826E-4,-1.2137444E-2,6.7261592E-3],"split_indices":[31,26,30,0,0,0,0],"split_type":[0,0,0,0,0,0,0],"sum_hessian":[7.422307E0,4.0237656E0,3.3985412E0,2.8609207E0,1.1628451E0,2.1767116E0,1.2218299E0],"tree_param":{"num_deleted":"0","num_feature":"53","num_nodes":"7","size_leaf_vector":"0"}},{"base_weights":[2.417092E-1,8.771352E-1,-7.373925E-1,1.0990084E0,1.17264606E-1,-1.601984E-1,-9.690051E-1],"categories":[],"categories_nodes":[],"categories_segments":[],"categories_sizes":[],"default_left":[1,1,1,0,0,0,0],"id":101,"left_children":[1,3,5,-1,-1,-1,-1],"loss_changes":[5.1328583E0,6.853504E-1,2.9677665E-1,0E0,0E0,0E0,0E0],"parents":[2147483647,0,0,1,1,2,2],"right_children":[2,4,6,-1,-1,-1,-1],"split_conditions":[1.104036E-1,7.7266455E-2,6.392424E-2,1.0990084E-2,1.1726461E-3,-1.601984E-3,-9.690051E-3],"split_indices":[4,42,1,0,0,0,0],"split_type":[0,0,0,0,0,0,0],"sum_hessian":[6.2106233E0,3.829478E0,2.3811455E0,2.618575E0,1.2109029E0,1.1663039E0,1.2148416E0],"tree_param":{"num_deleted":"0","num_feature":"53","num_nodes":"7","size_leaf_vector":"0"}},{"base_weights":[2.3042232E-1,6.8020725E-1,-8.250441E-1,9.55457E-1,4.736905E-2],"categories":[],"categories_nodes":[],"categories_segments":[],"categories_sizes":[],"default_left":[1,1,0,0,0],"id":102,"left_children":[1,3,-1,-1,-1],"loss_changes":[4.454213E0,1.0518086E0,0E0,0E0,0E0],"parents":[2147483647,0,0,1,1],"right_children":[2,4,-1,-1,-1],"split_conditions":[4.4544226E-1,2.5583705E-1,-8.2504405E-3,9.55457E-3,4.736905E-4],"split_indices":[48,31,0,0,0],"split_type":[0,0,0,0,0],"sum_hessian":[7.2004266E0,5.2981634E0,1.9022632E0,3.3369694E0,1.961194E0],"tree_param":{"num_deleted":"0","num_feature":"53","num_nodes":"5","size_leaf_vector":"0"}},{"base_weights":[-1.9421248E-1,8.631993E-1,-7.0137817E-1,-2.403643E-1,-1.0461849E0,-6.3601494E-1,2.6901945E-1],"categories":[],"categories_nodes":[],"categories_segments":[],"categories_sizes":[],"default_left":[1,0,1,1,0,0,0],"id":103,"left_children":[1,-1,3,5,-1,-1,-1],"loss_changes":[3.9624653E0,0E0,5.0874543E-1,8.451733E-1,0E0,0E0,0E0],"parents":[2147483647,0,0,2,2,3,3],"right_children":[2,-1,4,6,-1,-1,-1],"split_conditions":[-4.2911136E-1,8.631993E-3,3.56219E-1,-4.450871E-2,-1.0461849E-2,-6.360149E-3,2.6901944E-3],"split_indices":[31,0,1,33,0,0,0],"split_type":[0,0,0,0,0,0,0],"sum_hessian":[5.2598224E0,1.4774392E0,3.7823832E0,2.3446436E0,1.4377396E0,1.1797255E0,1.1649182E0],"tree_param":{"num_deleted":"0","num_feature":"53","num_nodes":"7","size_leaf_vector":"0"}},{"base_weights":[2.9882595E-1,6.6119236E-1,-5.368423E-1,-1.8081051E-1,1.15063E0],"categories":[],"categories_nodes":[],"categories_segments":[],"categories_sizes":[],"default_left":[1,1,0,0,0],"id":104,"left_children":[1,3,-1,-1,-1],"loss_changes":[2.488706E0,2.4182355E0,0E0,0E0,0E0],"parents":[2147483647,0,0,1,1],"right_children":[2,4,-1,-1,-1],"split_conditions":[3.94808E-1,-3.11447E-1,-5.3684227E-3,-1.808105E-3,1.15062995E-2],"split_indices":[18,18,0,0,0],"split_type":[0,0,0,0,0],"sum_hessian":[6.04631E0,4.3631334E0,1.6831765E0,1.8356874E0,2.5274458E0],"tree_param":{"num_deleted":"0","num_feature":"53","num_nodes":"5","size_leaf_vector":"0"}},{"base_weights":[2.2000322E-1,5.693102E-1,-6.93228E-1,1.1497127E0,-5.160266E-1],"categories":[],"categories_nodes":[],"categories_segments":[],"categories_sizes":[],"default_left":[1,1,0,0,0],"id":105,"left_children":[1,3,-1,-1,-1],"loss_changes":[2.6961672E0,4.226573E0,0E0,0E0,0E0],"parents":[2147483647,0,0,1,1],"right_children":[2,4,-1,-1,-1],"split_conditions":[4.4669506E-1,1.7323303E-1,-6.93228E-3,1.1497127E-2,-5.160266E-3],"split_indices":[48,42,0,0,0],"split_type":[0,0,0,0,0],"sum_hessian":[6.214794E0,4.767749E0,1.4470453E0,3.0678496E0,1.6998992E0],"tree_param":{"num_deleted":"0","num_feature":"53","num_nodes":"5","size_leaf_vector":"0"}},{"base_weights":[-5.665898E-2,9.6548516E-1,-6.1029714E-1,5.6631553E-1,-1.0967159E0],"categories":[],"categories_nodes":[],"categories_segments":[],"categories_sizes":[],"default_left":[1,0,1,0,0],"id":106,"left_children":[1,-1,3,-1,-1],"loss_changes":[4.6891546E0,0E0,3.6614108E0,0E0,0E0],"parents":[2147483647,0,0,2,2],"right_children":[2,-1,4,-1,-1],"split_conditions":[-2.9929748E-1,9.654852E-3,-2.6124215E-1,5.663155E-3,-1.0967159E-2],"split_indices":[12,0,19,0,0],"split_type":[0,0,0,0,0],"sum_hessian":[6.2449827E0,1.9327631E0,4.3122196E0,1.2132348E0,3.098985E0],"tree_param":{"num_deleted":"0","num_feature":"53","num_nodes":"5","size_leaf_vector":"0"}},{"base_weights":[3.1879666E-1,6.6183513E-1,-6.853006E-1,1.1777602E0,-3.266586E-1],"categories":[],"categories_nodes":[],"categories_segments":[],"categories_sizes":[],"default_left":[1,1,0,0,0],"id":107,"left_children":[1,3,-1,-1,-1],"loss_changes":[3.0940943E0,3.5582242E0,0E0,0E0,0E0],"parents":[2147483647,0,0,1,1],"right_children":[2,4,-1,-1,-1],"split_conditions":[3.3899665E-1,1.7410211E-1,-6.853006E-3,1.1777602E-2,-3.266586E-3],"split_indices":[48,42,0,0,0],"split_type":[0,0,0,0,0],"sum_hessian":[6.6660895E0,5.2226844E0,1.4434054E0,3.305811E0,1.9168732E0],"tree_param":{"num_deleted":"0","num_feature":"53","num_nodes":"5","size_leaf_vector":"0"}},{"base_weights":[-2.5669912E-2,9.5866233E-1,-5.438583E-1,5.2988476E-1,-9.588242E-1,-2.5479576E-1,-1.1460047E0],"categories":[],"categories_nodes":[],"categories_segments":[],"categories_sizes":[],"default_left":[1,0,1,0,1,0,0],"id":108,"left_children":[1,-1,3,-1,5,-1,-1],"loss_changes":[4.300882E0,0E0,2.9552703E0,0E0,2.7694154E-1,0E0,0E0],"parents":[2147483647,0,0,2,2,4,4],"right_children":[2,-1,4,-1,6,-1,-1],"split_conditions":[-2.9929748E-1,9.586623E-3,-2.6124215E-1,5.2988473E-3,-4.3785755E-2,-2.5479575E-3,-1.1460046E-2],"split_indices":[12,0,19,0,36,0,0],"split_type":[0,0,0,0,0,0,0],"sum_hessian":[6.409785E0,1.9174459E0,4.4923387E0,1.1750107E0,3.3173282E0,1.1926668E0,2.1246614E0],"tree_param":{"num_deleted":"0","num_feature":"53","num_nodes":"7","size_leaf_vector":"0"}},{"base_weights":[-5.9458055E-2,4.1254285E-1,-7.67313E-1,-2.5124064E-1,9.8781246E-1],"categories":[],"categories_nodes":[],"categories_segments":[],"categories_sizes":[],"default_left":[1,1,0,0,0],"id":109,"left_children":[1,3,-1,-1,-1],"loss_changes":[2.4412248E0,1.9533787E0,0E0,0E0,0E0],"parents":[2147483647,0,0,1,1],"right_children":[2,4,-1,-1,-1],"split_conditions":[5.146842E-1,-4.316645E-2,-7.67313E-3,-2.5124063E-3,9.878124E-3],"split_indices":[31,16,0,0,0],"split_type":[0,0,0,0,0],"sum_hessian":[5.359245E0,3.465576E0,1.8936688E0,1.8705167E0,1.5950592E0],"tree_param":{"num_deleted":"0","num_feature":"53","num_nodes":"5","size_leaf_vector":"0"}}]},"name":"gbtree"},"learner_model_param":{"base_score":"5E-1","boost_from_average":"1","num_class":"0","num_feature":"53","num_target":"1"},"objective":{"name":"binary:logistic","reg_loss_param":{"scale_pos_weight":"1"}}},"version":[1,7,7]}
